Workbook
Name UPDATE: #REF!

Sheet Raw Fs
B1: BERGER PAINTS
B2: Particulars | C2: 41699 | D2: 42064 | E2: 42430 | F2: 42795 | G2: 43160 | H2: 43525 | I2: 43891 | J2: 44256 | K2: 44621 | L2: 44986 | M2: 45352
B4: Equity Capital | C4: 69 | D4: 69 | E4: 69 | F4: 97 | G4: 97 | H4: 97 | I4: 97 | J4: 97 | K4: 97 | L4: 97 | M4: 117
B5: Reserves | C5: 1051 | D5: 1191 | E5: 1493 | F5: 1804 | G5: 2097 | H5: 2347 | I5: 2563 | J5: 3280 | K5: 3830 | L5: 4397 | M5: 5262
B6: Borrowings -
B7: Long term Borrowings | C7: 147 | D7: 251 | E7: 211 | F7: 262 | G7: 249 | H7: 239 | I7: 243 | J7: 166 | K7: 10 | L7: 8 | M7: 6
B8: Short term Borrowings | C8: 381 | D8: 358 | E8: 99 | F8: 144 | G8: 173 | H8: 245 | I8: 293 | J8: 210 | K8: 658 | L8: 760 | M8: 199
B9: Lease Liabilities | C9: 0 | D9: 0 | E9: 0 | F9: 0 | G9: 0 | H9: 233 | I9: 231 | J9: 258 | K9: 346 | L9: 421 | M9: 548
B10: Other Borrowings | C10: 95 | D10: 1 | E10: 45 | F10: 0 | G10: 0 | H10: 36 | I10: 0 | J10: 0 | K10: 0 | L10: 0 | M10: 0
B11: Other Liabilities -
B12: Non controlling int | C12: 0 | D12: 0 | E12: 0 | F12: 0 | G12: 0 | H12: 3 | I12: 7 | J12: 7 | K12: 7 | L12: 8 | M12: 10
B13: Trade Payables | C13: 544 | D13: 560 | E13: 670 | F13: 761 | G13: 955 | H13: 999 | I13: 1066 | J13: 1497 | K13: 1803 | L13: 1766 | M13: 1679
B14: Advance from Customers | C14: 9 | D14: 10 | E14: 11 | F14: 13 | G14: 19 | H14: 19 | I14: 17 | J14: 25 | K14: 24 | L14: 25 | M14: 29
B15: Other liability items | C15: 298 | D15: 276 | E15: 280 | F15: 358 | G15: 351 | H15: 338 | I15: 383 | J15: 378 | K15: 437 | L15: 485 | M15: 517
B16: Total Liabilities | C16: 2595 | D16: 2716 | E16: 2877 | F16: 3440 | G16: 3943 | H16: 4557 | I16: 4900 | J16: 5918 | K16: 7211 | L16: 7966 | M16: 8368
B18: Fixed Assets -
B19: Land | C19: 21 | D19: 23 | E19: 20 | F19: 21 | G19: 22 | H19: 61 | I19: 159 | J19: 170 | K19: 174 | L19: 183 | M19: 243
B20: Building | C20: 289 | D20: 344 | E20: 325 | F20: 405 | G20: 426 | H20: 656 | I20: 832 | J20: 884 | K20: 1004 | L20: 1626 | M20: 1769
B21: Plant Machinery | C21: 610 | D21: 709 | E21: 436 | F21: 607 | G21: 729 | H21: 835 | I21: 1011 | J21: 1206 | K21: 1306 | L21: 2023 | M21: 2181
B22: Equipments | C22: 74 | D22: 9 | E22: 7 | F22: 9 | G22: 11 | H22: 15 | I22: 19 | J22: 23 | K22: 27 | L22: 37 | M22: 44
B23: Computers | C23: 0 | D23: 69 | E23: 25 | F23: 36 | G23: 47 | H23: 49 | I23: 56 | J23: 58 | K23: 54 | L23: 61 | M23: 66
B24: Furniture n fittings | C24: 33 | D24: 36 | E24: 22 | F24: 26 | G24: 37 | H24: 40 | I24: 44 | J24: 47 | K24: 49 | L24: 55 | M24: 64
B25: Vehicles | C25: 24 | D25: 25 | E25: 13 | F25: 14 | G25: 19 | H25: 24 | I25: 27 | J25: 23 | K25: 20 | L25: 20 | M25: 22
B26: Intangible Assets | C26: 224 | D26: 198 | E26: 186 | F26: 179 | G26: 265 | H26: 269 | I26: 279 | J26: 288 | K26: 276 | L26: 282 | M26: 305
B27: Other fixed assets | C27: 47 | D27: 48 | E27: 14 | F27: 12 | G27: 16 | H27: 23 | I27: 25 | J27: 34 | K27: 43 | L27: 36 | M27: 44
B28: Gross Block | C28: 1322 | D28: 1461 | E28: 1048 | F28: 1310 | G28: 1571 | H28: 1971 | I28: 2452 | J28: 2734 | K28: 2955 | L28: 4324 | M28: 4736
B29: Accumulated Depreciation | C29: 458 | D29: 531 | E29: 85 | F29: 174 | G29: 304 | H29: 388 | I29: 536 | J29: 690 | K29: 768 | L29: 992 | M29: 1236
B30: Net Block | C30: =C28-C29 -> 864 | D30: =D28-D29 -> 930 | E30: =E28-E29 -> 963 | F30: =F28-F29 -> 1136 | G30: =G28-G29 -> 1267 | H30: =H28-H29 -> 1583 | I30: =I28-I29 -> 1916 | J30: =J28-J29 -> 2044 | ... M30: =M28-M29 -> 3500
B32: CWIP | C32: 133 | D32: 100 | E32: 51 | F32: 62 | G32: 97 | H32: 170 | I32: 178 | J32: 107 | K32: 606 | L32: 111 | M32: 189
B33: Investments | C33: 91 | D33: 134 | E33: 348 | F33: 472 | G33: 333 | H33: 395 | I33: 315 | J33: 356 | K33: 234 | L33: 183 | M33: 255
B34: Other Assets -
B35: Inventories | C35: 696 | D35: 719 | E35: 733 | F35: 935 | G35: 1007 | H35: 1234 | I35: 1278 | J35: 1616 | K35: 2316 | L35: 2319 | M35: 2180
B36: Trade receivables | C36: 486 | D36: 535 | E36: 545 | F36: 578 | G36: 692 | H36: 671 | I36: 714 | J36: 1020 | K36: 1054 | L36: 1243 | M36: 1302
B37: Cash Equivalents | C37: 184 | D37: 170 | E37: 105 | F37: 102 | G37: 205 | H37: 238 | I37: 220 | J37: 440 | K37: 313 | L37: 245 | M37: 451
B38: Loans n Advances | C38: 0 | D38: 0 | E38: 8 | F38: 11 | G38: 9 | H38: 11 | I38: 12 | J38: 13 | K38: 12 | L38: 26 | M38: 26
B39: Other asset items | C39: 142 | D39: 126 | E39: 123 | F39: 142 | G39: 331 | H39: 255 | I39: 266 | J39: 323 | K39: 490 | L39: 509 | M39: 465
B40: Total Assets | C40: 2595 | D40: 2716 | E40: 2877 | F40: 3440 | G40: 3943 | H40: 4557 | I40: 4900 | J40: 5918 | K40: 7211 | L40: 7966 | M40: 8368
B43: Particulars | C43: 41699 | D43: 42064 | E43: 42430 | F43: 42795 | G43: 43160 | H43: 43525 | I43: 43891 | J43: 44256 | K43: 44621 | L43: 44986 | M43: 45352
B44: Cash from Operating Activity -
B45: Profit from operations | C45: 438 | D45: 524 | E45: 659 | F45: 742 | G45: 827 | H45: 946 | I45: 1087 | J45: 1216 | K45: 1363 | L45: 1543 | M45: 1909
B46: Receivables | C46: -101 | D46: -49 | E46: -44 | F46: -34 | G46: -114 | H46: 21 | I46: -43 | J46: -306 | K46: -42 | L46: -212 | M46: -103
B47: Inventory | C47: -60 | D47: -24 | E47: -39 | F47: -203 | G47: -72 | H47: -226 | I47: -45 | J47: -338 | K47: -700 | L47: -3 | M47: 139
B48: Payables | C48: 136 | D48: 15 | E48: 132 | F48: 92 | G48: 194 | H48: 46 | I48: 63 | J48: 433 | K48: 314 | L48: -37 | M48: -83
B49: Loans Advances | C49: 0 | D49: 53 | E49: 0 | F49: 2 | G49: 4 | H49: -1 | I49: -5 | J49: -30 | K49: -8 | L49: -41 | M49: 15
B50: Other WC items | C50: 0 | D50: 16 | E50: 65 | F50: 16 | G50: -140 | H50: 69 | I50: -71 | J50: 72 | K50: -62 | L50: 35 | M50: 61
B51: Working capital changes | C51: -26 | D51: 12 | E51: 114 | F51: -128 | G51: -128 | H51: -92 | I51: -100 | J51: -168 | K51: -498 | L51: -259 | M51: 30
B52: Direct taxes | C52: -102 | D52: -122 | E52: -178 | F52: -220 | G52: -277 | H52: -243 | I52: -263 | J52: -252 | K52: -299 | L52: -308 | M52: -349
B54: Cash from Investing Activity -
B55: Fixed assets purchased | C55: -243 | D55: -162 | E55: -122 | F55: -269 | G55: -293 | H55: -293 | I55: -435 | J55: -186 | K55: -774 | L55: -748 | M55: -275
B56: Fixed assets sold | C56: 1 | D56: 1 | E56: 4 | F56: 4 | G56: 3 | H56: 2 | I56: 4 | J56: 1 | K56: 14 | L56: 4 | M56: 4
B57: Investments purchased | C57: -90 | D57: -758 | E57: -148 | F57: -4094 | G57: -1988 | H57: -2130 | I57: -3208 | J57: -890 | K57: -1063 | L57: -751 | M57: -1597
B58: Investments sold | C58: 11 | D58: 720 | E58: 0 | F58: 4056 | G58: 2150 | H58: 2126 | I58: 3297 | J58: 869 | K58: 1193 | L58: 788 | M58: 1572
B59: Interest received | C59: 21 | D59: 15 | E59: 12 | F59: 5 | G59: 6 | H59: 18 | I59: 17 | J59: 14 | K59: 23 | L59: 13 | M59: 16
B60: Dividends received | C60: 0 | D60: 0 | E60: 0 | F60: 0 | G60: 0 | H60: 0 | I60: 0 | J60: 4 | K60: 3 | L60: 4 | M60: 2
B61: Invest in subsidiaries | C61: -1 | D61: 0 | E61: 0 | F61: 0 | G61: 0 | H61: 0 | I61: 0 | J61: 0 | K61: 0 | L61: 0 | M61: 0
B62: Investment in group cos | C62: 0 | D62: 0 | E62: -6 | F62: -57 | G62: 0 | H62: 0 | I62: 0 | J62: -20 | K62: 0 | L62: 0 | M62: 0
B63: Redemp n Canc of Shares | C63: 0 | D63: 0 | E63: 0 | F63: 0 | G63: 2 | H63: 0 | I63: 0 | J63: 0 | K63: 0 | L63: 0 | M63: 0
B64: Acquisition of companies | C64: 0 | D64: 0 | E64: 0 | F64: 0 | G64: 0 | H64: -41 | I64: 0 | J64: 0 | K64: 0 | L64: 0 | M64: 0
B65: Other investing items | C65: 0 | D65: 0 | E65: 0 | F65: 46 | G65: -63 | H65: -61 | I65: 102 | J65: -250 | K65: 83 | L65: 90 | M65: -120
B67: Cash from Financing Activity -
B68: Proceeds from shares | C68: 0 | D68: 0 | E68: 0 | F68: 0 | G68: 0 | H68: 0 | I68: 0 | J68: 0 | K68: 0 | L68: 0 | M68: 0
B69: Proceeds from borrowings | C69: 96 | D69: 10 | E69: 0 | F69: 1131 | G69: 2578 | H69: 3242 | I69: 3538 | J69: 1457 | K69: 3114 | L69: 8414 | M69: 6465
B70: Repayment of borrowings | C70: -43 | D70: -24 | E70: -232 | F70: -1053 | G70: -2659 | H70: -3123 | I70: -3437 | J70: -1582 | K70: -2822 | L70: -8314 | M70: -7027
B71: Interest paid fin | C71: -42 | D71: -45 | E71: -27 | F71: -16 | G71: -25 | H71: -30 | I71: -31 | J71: -25 | K71: -23 | L71: -61 | M71: -36
B72: Dividends paid | C72: -62 | D72: -138 | E72: -108 | F72: -117 | G72: -205 | H72: -211 | I72: -382 | J72: -29 | K72: -272 | L72: -301 | M72: -311
B73: Financial liabilities | C73: 0 | D73: 0 | E73: 0 | F73: 0 | G73: 0 | H73: -80 | I73: -118 | J73: -75 | K73: -76 | L73: -100 | M73: -160
B74: Other financing items | C74: 0 | D74: 0 | E74: 0 | F74: -27 | G74: 110 | H74: -57 | I74: -49 | J74: -26 | K74: 0 | L74: 0 | M74: 0
B75: Net Cash Flow | C75: -43 | D75: 32 | E75: -32 | F75: 4 | G75: 38 | H75: -27 | I75: 22 | J75: 57 | K75: -33 | L75: 13 | M75: 124
C78: 41699 | D78: 42064 | E78: 42430 | F78: 42795 | G78: 43160 | H78: 43525 | I78: 43891 | J78: 44256 | K78: 44621 | L78: 44986 | M78: 45352
B79: Sales | C79: 3732 | D79: 4170 | E79: 4223 | F79: 4552 | G79: 5166 | H79: 6062 | I79: 6366 | J79: 6818 | K79: 8762 | L79: 10568 | M79: 11199
B80: Expenses | C80: 3300 | D80: 3659 | E80: 3578 | F80: 3833 | G80: 4359 | H80: 5127 | I80: 5313 | J80: 5635 | K80: 7431 | L80: 9090 | M80: 9338
B81: Operating Profit | C81: 431 | D81: 511 | E81: 645 | F81: 719 | G81: 807 | H81: 935 | I81: 1053 | J81: 1182 | K81: 1331 | L81: 1478 | M81: 1861
B82: OPM % | C82: 0.12 | D82: 0.12 | E82: 0.15 | F82: 0.16 | G82: 0.16 | H82: 0.15 | I82: 0.17 | J82: 0.17 | K82: 0.15 | L82: 0.14 | M82: 0.17
B83: Other Income | C83: 36 | D83: 36 | E83: 40 | F83: 108 | G83: 46 | H83: 60 | I83: 69 | J83: 51 | K83: 68 | L83: 48 | M83: 105
B84: Interest | C84: 47 | D84: 50 | E84: 27 | F84: 16 | G84: 25 | H84: 47 | I84: 47 | J84: 44 | K84: 51 | L84: 99 | M84: 78
B85: Depreciation | C85: 71 | D85: 92 | E85: 99 | F85: 108 | G85: 124 | H85: 182 | I85: 191 | J85: 211 | K85: 227 | L85: 264 | M85: 331
B86: Profit before tax | C86: 350 | D86: 404 | E86: 559 | F86: 703 | G86: 705 | H86: 765 | I86: 883 | J86: 979 | K86: 1122 | L86: 1162 | M86: 1557
B87: Tax % | C87: 0.29 | D87: 0.34 | E87: 0.34 | F87: 0.33 | G87: 0.35 | H87: 0.35 | I87: 0.26 | J87: 0.26 | K87: 0.26 | L87: 0.26 | M87: 0.25
B88: Net Profit | C88: 249 | D88: 265 | E88: 371 | F88: 474 | G88: 461 | H88: 494 | I88: 656 | J88: 720 | K88: 833 | L88: 860 | M88: 1170
B89: EPS in Rs | C89: 2.14 | D89: 2.27 | E89: 3.18 | F89: 4.07 | G89: 3.95 | H89: 4.24 | I89: 5.64 | J89: 6.17 | K89: 7.14 | L89: 7.37 | M89: 10.02
B90: Dividend Payout % | C90: 0.31 | D90: 0.33 | E90: 0.31 | F90: 0.36 | G90: 0.38 | H90: 0.37 | I90: 0.32 | J90: 0.38 | K90: 0.36 | L90: 0.36 | M90: 0.35

Sheet Intrinsic Growth
B2: Calculations of ROIC | C2: 43891 | D2: 44256 | E2: 44621 | F2: 44986 | G2: 45352
B4: Current Assets
B5: ='Raw Fs'!B35 -> Inventories | C5: ='Raw Fs'!I35 -> 1278 | D5: ='Raw Fs'!J35 -> 1616 | E5: ='Raw Fs'!K35 -> 2316 | F5: ='Raw Fs'!L35 -> 2319 | G5: ='Raw Fs'!M35 -> 2180
B6: ='Raw Fs'!B36 -> Trade receivables | C6: ='Raw Fs'!I36 -> 714 | D6: ='Raw Fs'!J36 -> 1020 | E6: ='Raw Fs'!K36 -> 1054 | F6: ='Raw Fs'!L36 -> 1243 | G6: ='Raw Fs'!M36 -> 1302
B7: ='Raw Fs'!B37 -> Cash Equivalents | C7: ='Raw Fs'!I37 -> 220 | D7: ='Raw Fs'!J37 -> 440 | E7: ='Raw Fs'!K37 -> 313 | F7: ='Raw Fs'!L37 -> 245 | G7: ='Raw Fs'!M37 -> 451
B8: ='Raw Fs'!B38 -> Loans n Advances | C8: ='Raw Fs'!I38 -> 12 | D8: ='Raw Fs'!J38 -> 13 | E8: ='Raw Fs'!K38 -> 12 | F8: ='Raw Fs'!L38 -> 26 | G8: ='Raw Fs'!M38 -> 26
B9: ='Raw Fs'!B39 -> Other asset items | C9: ='Raw Fs'!I39 -> 266 | D9: ='Raw Fs'!J39 -> 323 | E9: ='Raw Fs'!K39 -> 490 | F9: ='Raw Fs'!L39 -> 509 | G9: ='Raw Fs'!M39 -> 465
B10: Total Current Assets | C10: =SUM(C5:C9) -> 2490 | D10: =SUM(D5:D9) -> 3412 | E10: =SUM(E5:E9) -> 4185 | F10: =SUM(F5:F9) -> 4342 | G10: =SUM(G5:G9) -> 4424
B12: Current Liabilities
B13: ='Raw Fs'!B13 -> Trade Payables | C13: ='Raw Fs'!I13 -> 1066 | D13: ='Raw Fs'!J13 -> 1497 | E13: ='Raw Fs'!K13 -> 1803 | F13: ='Raw Fs'!L13 -> 1766 | G13: ='Raw Fs'!M13 -> 1679
B14: ='Raw Fs'!B14 -> Advance from Customers | C14: ='Raw Fs'!I14 -> 17 | D14: ='Raw Fs'!J14 -> 25 | E14: ='Raw Fs'!K14 -> 24 | F14: ='Raw Fs'!L14 -> 25 | G14: ='Raw Fs'!M14 -> 29
B15: ='Raw Fs'!B15 -> Other liability items | C15: ='Raw Fs'!I15 -> 383 | D15: ='Raw Fs'!J15 -> 378 | E15: ='Raw Fs'!K15 -> 437 | F15: ='Raw Fs'!L15 -> 485 | G15: ='Raw Fs'!M15 -> 517
B16: Total Current Liabilities | C16: =SUM(C13:C15) -> 1466 | D16: =SUM(D13:D15) -> 1900 | E16: =SUM(E13:E15) -> 2264 | F16: =SUM(F13:F15) -> 2276 | G16: =SUM(G13:G15) -> 2225
A18: # | B18: Net Working Capital | C18: =C10-C16 -> 1024 | D18: =D10-D16 -> 1512 | E18: =E10-E16 -> 1921 | F18: =F10-F16 -> 2066 | G18: =G10-G16 -> 2199
B20: Non Current Asstes
B21: ='Raw Fs'!B19 -> Land | C21: ='Raw Fs'!C19 -> 21 | D21: ='Raw Fs'!D19 -> 23 | E21: ='Raw Fs'!E19 -> 20 | F21: ='Raw Fs'!F19 -> 21 | G21: ='Raw Fs'!G19 -> 22
B22: ='Raw Fs'!B20 -> Building | C22: ='Raw Fs'!C20 -> 289 | D22: ='Raw Fs'!D20 -> 344 | E22: ='Raw Fs'!E20 -> 325 | F22: ='Raw Fs'!F20 -> 405 | G22: ='Raw Fs'!G20 -> 426
B23: ='Raw Fs'!B21 -> Plant Machinery | C23: ='Raw Fs'!C21 -> 610 | D23: ='Raw Fs'!D21 -> 709 | E23: ='Raw Fs'!E21 -> 436 | F23: ='Raw Fs'!F21 -> 607 | G23: ='Raw Fs'!G21 -> 729
B24: ='Raw Fs'!B22 -> Equipments | C24: ='Raw Fs'!C22 -> 74 | D24: ='Raw Fs'!D22 -> 9 | E24: ='Raw Fs'!E22 -> 7 | F24: ='Raw Fs'!F22 -> 9 | G24: ='Raw Fs'!G22 -> 11
B25: ='Raw Fs'!B23 -> Computers | C25: ='Raw Fs'!C23 -> 0 | D25: ='Raw Fs'!D23 -> 69 | E25: ='Raw Fs'!E23 -> 25 | F25: ='Raw Fs'!F23 -> 36 | G25: ='Raw Fs'!G23 -> 47
B26: ='Raw Fs'!B24 -> Furniture n fittings | C26: ='Raw Fs'!C24 -> 33 | D26: ='Raw Fs'!D24 -> 36 | E26: ='Raw Fs'!E24 -> 22 | F26: ='Raw Fs'!F24 -> 26 | G26: ='Raw Fs'!G24 -> 37
B27: ='Raw Fs'!B25 -> Vehicles | C27: ='Raw Fs'!C25 -> 24 | D27: ='Raw Fs'!D25 -> 25 | E27: ='Raw Fs'!E25 -> 13 | F27: ='Raw Fs'!F25 -> 14 | G27: ='Raw Fs'!G25 -> 19
B28: ='Raw Fs'!B26 -> Intangible Assets | C28: ='Raw Fs'!C26 -> 224 | D28: ='Raw Fs'!D26 -> 198 | E28: ='Raw Fs'!E26 -> 186 | F28: ='Raw Fs'!F26 -> 179 | G28: ='Raw Fs'!G26 -> 265
B29: ='Raw Fs'!B27 -> Other fixed assets | C29: ='Raw Fs'!C27 -> 47 | D29: ='Raw Fs'!D27 -> 48 | E29: ='Raw Fs'!E27 -> 14 | F29: ='Raw Fs'!F27 -> 12 | G29: ='Raw Fs'!G27 -> 16
B30: ='Raw Fs'!B28 -> Gross Block | C30: ='Raw Fs'!C28 -> 1322 | D30: ='Raw Fs'!D28 -> 1461 | E30: ='Raw Fs'!E28 -> 1048 | F30: ='Raw Fs'!F28 -> 1310 | G30: ='Raw Fs'!G28 -> 1571
B31: ='Raw Fs'!B29 -> Accumulated Depreciation | C31: ='Raw Fs'!C29 -> 458 | D31: ='Raw Fs'!D29 -> 531 | E31: ='Raw Fs'!E29 -> 85 | F31: ='Raw Fs'!F29 -> 174 | G31: ='Raw Fs'!G29 -> 304
A32: # | B32: Net Non Current Assets | C32: ='Raw Fs'!C30 -> 864 | D32: ='Raw Fs'!D30 -> 930 | E32: ='Raw Fs'!E30 -> 963 | F32: ='Raw Fs'!F30 -> 1136 | G32: ='Raw Fs'!G30 -> 1267
A34: # | B34: Invested Capital | C34: =C18+C32 -> 1888 | D34: =D18+D32 -> 2442 | E34: =E18+E32 -> 2884 | F34: =F18+F32 -> 3202 | G34: =G18+G32 -> 3466
B35: EBIT | C35: ='Raw Fs'!I86+'Raw Fs'!I84 -> 930 | D35: ='Raw Fs'!J86+'Raw Fs'!J84 -> 1023 | E35: ='Raw Fs'!K86+'Raw Fs'!K84 -> 1173 | F35: ='Raw Fs'!L86+'Raw Fs'!L84 -> 1261 | G35: ='Raw Fs'!M86+'Raw Fs'!M84 -> 1635
A37: # | B37: ROIC | C37: =C35/C34 -> 0.49258475 | D37: =D35/D34 -> 0.41891892 | E37: =E35/E34 -> 0.40672677 | F37: =F35/F34 -> 0.39381636 | G37: =G35/G34 -> 0.47172533
A40: # | B40: Calculations of Reinvestment Rate | C40: 43891 | D40: 44256 | E40: 44621 | F40: 44986 | G40: 45352
B42: Net Capex | C42: =-SUM('Raw Fs'!I55:I56) -> 431 | D42: =-SUM('Raw Fs'!J55:J56) -> 185 | E42: =-SUM('Raw Fs'!K55:K56) -> 760 | F42: =-SUM('Raw Fs'!L55:L56) -> 744 | G42: =-SUM('Raw Fs'!M55:M56) -> 271
B43: Change in Working Capital | D43: =D18-C18 -> 488 | E43: =E18-D18 -> 409 | F43: =F18-E18 -> 145 | G43: =G18-F18 -> 133
B45: EBIT | C45: =C35 -> 930 | D45: =D35 -> 1023 | E45: =E35 -> 1173 | F45: =F35 -> 1261 | G45: =G35 -> 1635
B46: Marginal Tax Rate | C46: 0.25 | D46: 0.25 | E46: 0.25 | F46: 0.25 | G46: 0.25
B47: EBIT(1-Tax) | C47: =C45*(1-C46) -> 697.5 | D47: =D45*(1-D46) -> 767.25 | E47: =E45*(1-E46) -> 879.75 | F47: =F45*(1-F46) -> 945.75 | G47: =G45*(1-G46) -> 1226.25
B49: Reinvestment | D49: =SUM(D42:D43) -> 673 | E49: =SUM(E42:E43) -> 1169 | F49: =SUM(F42:F43) -> 889 | G49: =SUM(G42:G43) -> 404
B50: Reinvestment Rate | D50: =D49/D47 -> 0.87715868 | E50: =E49/E47 -> 1.3287866 | F50: =F49/F47 -> 0.93999471 | G50: =G49/G47 -> 0.32945973
A53: # | B53: Calculation Of Growth Rate | C53: 43891 | D53: 44256 | E53: 44621 | F53: 44986 | G53: 45352
B55: Reinvestment Rate | D55: =D50 -> 0.87715868 | E55: =E50 -> 1.3287866 | F55: =F50 -> 0.93999471 | G55: =G50 -> 0.32945973
B56: ROIC | D56: =D37 -> 0.41891892 | E56: =E37 -> 0.40672677 | F56: =F37 -> 0.39381636 | G56: =G37 -> 0.47172533
B57: Intrinsic Growth | D57: =D55*D56 -> 0.36745837 | E57: =E55*E56 -> 0.54045307 | F57: =F55*F56 -> 0.3701853 | G57: =G55*G56 -> 0.1554145
F58: 4 Year Average | G58: =AVERAGE(D57:G57) -> 0.35837781
F59: 4 Year Median | G59: =MEDIAN(D57:G57) -> 0.36882183

Sheet Sheet1
