Workbook
Name UPDATE: 'Data Sheet'!$E$1

Sheet Data Sheet
A1: COMPANY NAME | B1: AVENUE SUPERMARTS LTD | E1: =IF(B2<>B3, "A NEW VERSION OF THE WORKSHEET IS AVAILABLE", "")
A2: LATEST VERSION | B2: 2.1 | E2: PLEASE DO NOT MAKE ANY CHANGES TO THIS SHEET
A3: CURRENT VERSION | B3: 2.1
A5: META
A6: Number of shares | B6: =IF(B9>0, B9/B8, 0) -> 65.111799
A7: Face Value | B7: 10
A8: Current Price | B8: 4372.3
A9: Market Capitalization | B9: 284688.32
A15: PROFIT & LOSS
A16: Report Date | B16: 42460 | C16: 42825 | D16: 43190 | E16: 43555 | F16: 43921 | G16: 44286 | H16: 44651 | I16: 45016 | J16: 45382 | K16: 45747
A17: Sales | B17: 8583.76 | C17: 11897.7 | D17: 15033.2 | E17: 20004.52 | F17: 24870.2 | G17: 24143.06 | H17: 30976.27 | I17: 42839.56 | J17: 50788.83 | K17: 59358.05
A18: Raw Material Cost | B18: 7435.62 | C18: 10357.25 | D18: 12846.95 | E18: 17445.49 | F18: 21441.68 | G18: 20855.56 | H18: 26891.77 | I18: 36884.77 | J18: 43958.31 | K18: 51668.76
A19: Change in Inventory | B19: 132.08 | C19: 276.22 | D19: 211.31 | E19: 444.65 | F19: 338.75 | G19: 300.88 | H19: 494.38 | I19: 500.82 | J19: 683.77 | K19: 1117.06
A20: Power and Fuel | B20: 79.24 | C20: 99.41 | D20: 121.26 | E20: 152.8 | F20: 188.24 | G20: 174.2 | H20: 207.86 | I20: 314.62 | J20: 376.59
A21: Other Mfr. Exp | B21: 241.36 | C21: 332.9 | D21: 373.72 | E21: 499.72 | F21: 645.96 | G21: 746.43 | H21: 805.85 | I21: 1116.56 | J21: 1323.43
A22: Employee Cost | B22: 149.04 | C22: 192.67 | D22: 283.14 | E22: 356.17 | F22: 457.14 | G22: 537.58 | H22: 617.36 | I22: 748.16 | J22: 907.82 | K22: 1165.9
A23: Selling and admin | B23: 647.37 | C23: 71.24 | D23: 96 | E23: 135.84 | F23: 119.23 | G23: 108.69 | H23: 143.41 | I23: 212.04 | J23: 274.43
A24: Other Expenses | B24: -501.25 | C24: 151.27 | D24: 170.58 | E24: 225.84 | F24: 228.39 | G24: 276.65 | H24: 302.05 | I24: 425.46 | J24: 526.38 | K24: 3153.12
A25: Other Income | B25: 17.02 | C25: 27.7 | D25: 87.75 | E25: 48.33 | F25: 59.99 | G25: 194.43 | H25: 113.64 | I25: 127.6 | J25: 144.58 | K25: 124.31
A26: Depreciation | B26: 98.43 | C26: 127.82 | D26: 159 | E26: 212.49 | F26: 374.41 | G26: 414.16 | H26: 498.08 | I26: 638.87 | J26: 730.76 | K26: 869.52
A27: Interest | B27: 91.34 | C27: 121.98 | D27: 59.54 | E27: 47.21 | F27: 69.12 | G27: 41.65 | H27: 53.79 | I27: 67.41 | J27: 58.13 | K27: 69.45
A28: Profit before tax | B28: 491.71 | C28: 747.08 | D28: 1222.07 | E28: 1421.94 | F28: 1744.77 | G28: 1483.45 | H28: 2064.12 | I28: 3060.09 | J28: 3461.33 | K28: 3672.67
A29: Tax | B29: 171.47 | C29: 268.28 | D29: 415.79 | E29: 519.48 | F29: 443.79 | G29: 384.02 | H29: 571.72 | I29: 681.75 | J29: 925.72 | K29: 965.22
A30: Net profit | B30: 320.24 | C30: 478.75 | D30: 806.26 | E30: 902.54 | F30: 1301.08 | G30: 1099.49 | H30: 1492.55 | I30: 2378.51 | J30: 2536.17 | K30: 2708.02
A31: Dividend Amount
A40: Quarters
A41: Report Date | B41: 44926 | C41: 45016 | D41: 45107 | E41: 45199 | F41: 45291 | G41: 45382 | H41: 45473 | I41: 45565 | J41: 45657 | K41: 45747
A42: Sales | B42: 11569.05 | C42: 10594.11 | D42: 11865.44 | E42: 12624.37 | F42: 13572.47 | G42: 12726.55 | H42: 14069.14 | I42: 14444.5 | J42: 15972.55 | K42: 14871.86
A43: Expenses | B43: 10603.79 | C43: 9822.6 | D43: 10830.17 | E43: 11619.4 | F43: 12452.58 | G43: 11782.91 | H43: 12847.89 | I43: 13350.73 | J43: 14755.31 | K43: 13916.79
A44: Other Income | B44: 31.56 | C44: 33.07 | D44: 38.74 | E44: 36.92 | F44: 32.92 | G44: 37.87 | H44: 41.6 | I44: 33.52 | J44: 24.14 | K44: 25.05
A45: Depreciation | B45: 168.09 | C45: 164.08 | D45: 162.18 | E45: 174.36 | F45: 189.33 | G45: 204.89 | H45: 192.76 | I45: 207.78 | J45: 228.12 | K45: 240.86
A46: Interest | B46: 16.98 | C46: 15.53 | D46: 14.57 | E46: 15.59 | F46: 14.55 | G46: 13.42 | H46: 15.96 | I46: 16.32 | J46: 18.21 | K46: 18.96
A47: Profit before tax | B47: 811.75 | C47: 624.97 | D47: 897.26 | E47: 851.94 | F47: 948.93 | G47: 763.2 | H47: 1054.13 | I47: 903.19 | J47: 995.05 | K47: 720.3
A48: Tax | B48: 222.11 | C48: 164.87 | D48: 238.55 | E48: 228.59 | F48: 258.52 | G48: 200.06 | H48: 280.45 | I48: 243.75 | J48: 271.51 | K48: 169.51
A49: Net profit | B49: 589.68 | C49: 460.13 | D49: 658.75 | E49: 623.56 | F49: 690.61 | G49: 563.25 | H49: 773.82 | I49: 659.58 | J49: 723.72 | K49: 550.9
A50: Operating Profit | B50: 965.26 | C50: 771.51 | D50: 1035.27 | E50: 1004.97 | F50: 1119.89 | G50: 943.64 | H50: 1221.25 | I50: 1093.77 | J50: 1217.24 | K50: 955.07
A55: BALANCE SHEET
A56: Report Date | B56: 42460 | C56: 42825 | D56: 43190 | E56: 43555 | F56: 43921 | G56: 44286 | H56: 44651 | I56: 45016 | J56: 45382 | K56: 45747
A57: Equity Share Capital | B57: 561.54 | C57: 624.08 | D57: 624.08 | E57: 624.08 | F57: 647.77 | G57: 647.77 | H57: 647.77 | I57: 648.26 | J57: 650.73 | K57: 650.73
A58: Reserves | B58: 958.9 | C58: 3217.7 | D58: 4044.97 | E58: 4963.37 | F58: 10431.97 | G58: 11535.94 | H58: 13029.87 | I58: 15430.44 | J58: 18047.09 | K58: 20777.02
A59: Borrowings | B59: 1192.34 | C59: 1497.32 | D59: 439.25 | E59: 700.15 | F59: 333.19 | G59: 392.71 | H59: 646.94 | I59: 642.98 | J59: 592.16 | K59: 819.62
A60: Other Liabilities | B60: 388.78 | C60: 480.18 | D60: 539.92 | E60: 717.9 | F60: 663.23 | G60: 1078.63 | H60: 1146.4 | I60: 1382.84 | J60: 1882.5 | K60: 2072.92
A61: Total | B61: 3101.56 | C61: 5819.28 | D61: 5648.22 | E61: 7005.5 | F61: 12076.16 | G61: 13655.05 | H61: 15470.98 | I61: 18104.52 | J61: 21172.48 | K61: 24320.29
A62: Net Block | B62: 2093.52 | C62: 2577.75 | D62: 3399.97 | E62: 4400.37 | F62: 5948.03 | G62: 7008.8 | H62: 9260.02 | I62: 11340.48 | J62: 13415 | K62: 16206.46
A63: Capital Work in Progress | B63: 81.69 | C63: 152.89 | D63: 147.07 | E63: 376.84 | F63: 364.4 | G63: 1019.59 | H63: 1129.34 | I63: 829.16 | J63: 935.22 | K63: 1099.35
A64: Investments | B64: 29.33 | C64: 25.69 | D64: 68.18 | E64: 16.53 | F64: 14.68 | G64: 2.95 | H64: 5.94 | I64: 202.2 | J64: 106.67 | K64: 3.26
A65: Other Assets | B65: 897.02 | C65: 3062.95 | D65: 2033 | E65: 2211.76 | F65: 5749.05 | G65: 5623.71 | H65: 5075.68 | I65: 5732.68 | J65: 6715.59 | K65: 7011.22
A66: Total | B66: 3101.56 | C66: 5819.28 | D66: 5648.22 | E66: 7005.5 | F66: 12076.16 | G66: 13655.05 | H66: 15470.98 | I66: 18104.52 | J66: 21172.48 | K66: 24320.29
A67: Receivables | B67: 8.42 | C67: 21 | D67: 33.52 | E67: 64.37 | F67: 19.55 | G67: 43.58 | H67: 66.89 | I67: 62.16 | J67: 166.37 | K67: 153.79
... A69: Cash & Bank | B69: 35.1 | C69: 1884.29 | D69: 560.18 | E69: 219.07 | F69: 107.88 | G69: 1445.58 | H69: 298.58 | I69: 1408.33 | J69: 638.18 | K69: 358.2
A70: No. of Equity Shares | B70: 561542680 | C70: 624084486 | D70: 624084486 | E70: 624084486 | F70: 647774691 | G70: 647774691 | H70: 647774691 | I70: 648263978 | J70: 650733068
A71: New Bonus Shares
A72: Face value | B72: 10 | C72: 10 | D72: 10 | E72: 10 | F72: 10 | G72: 10 | H72: 10 | I72: 10 | J72: 10 | K72: 10
A80: CASH FLOW:
A81: Report Date | B81: 42460 | C81: 42825 | D81: 43190 | E81: 43555 | F81: 43921 | G81: 44286 | H81: 44651 | I81: 45016 | J81: 45382 | K81: 45747
A82: Cash from Operating Activity | B82: 433.47 | C82: 455.28 | D82: 729.99 | E82: 806.84 | F82: 1280.14 | G82: 1375.14 | H82: 1372.35 | I82: 2630.27 | J82: 2745.84 | K82: 2462.97
A83: Cash from Investing Activity | B83: -632.89 | C83: -2481.61 | D83: 463.55 | E83: -958.37 | F83: -4656.56 | G83: -1110 | H83: -1289.49 | I83: -2313.1 | J83: -2468.23 | K83: -2185.31
A84: Cash from Financing Activity | B84: 196.44 | C84: 2025.26 | D84: -1159.06 | E84: 208.98 | F84: 3357.42 | G84: -179.5 | H84: -179.24 | I84: -205.14 | J84: -147.64 | K84: -259.3
A85: Net Cash Flow | B85: -2.98 | C85: -1.07 | D85: 34.48 | E85: 57.45 | F85: -19 | G85: 85.64 | H85: -96.38 | I85: 112.03 | J85: 129.97 | K85: 18.36
A90: PRICE: | C90: 637.85 | D90: 1324.8 | E90: 1471.1 | F90: 2187.5 | G90: 2859.05 | H90: 4003.35 | I90: 3401.05 | J90: 4525.6 | K90: 4083.2
A92: DERIVED:
A93: Adjusted Equity Shares in Cr | B93: 56.15 | C93: 62.41 | D93: 62.41 | E93: 62.41 | F93: 64.78 | G93: 64.78 | H93: 64.78 | I93: 64.83 | J93: 65.07 | K93: 65.07

Sheet Cash Flow Data
B1: 42430 | C1: 42795 | D1: 43160 | E1: 43525 | F1: 43891 | G1: 44256 | H1: 44621 | I1: 44986 | J1: 45352 | K1: 45717
A2: Cash from Operating Activity - | B2: 2385 | C2: 183 | D2: 682 | E2: -4347 | F2: -1457 | G2: 17909 | H2: 9248 | I2: -7074 | J2: -5630 | K2: 3176
A3: Profit from operations | B3: 7595 | C3: 7911 | D3: 10159 | E3: 11112 | F3: 7774 | G3: 7588 | H3: 10515 | I3: 15642 | J3: 17541 | K3: 22050
A4: Receivables | B4: 177 | C4: -8609 | D4: -11918 | E4: -13712 | F4: -1516 | G4: 4896 | H4: -2506 | I4: -21702 | J4: -21777 | K4: -3782
A5: Inventory | B5: -1113 | C5: 241 | D5: -256 | E5: -2276 | F5: 1316 | G5: 226 | H5: -2173 | I5: -5252 | J5: -1753 | K5: -1646
A6: Payables | B6: 1939 | C6: 2645 | D6: 5361 | E6: 3466 | F6: -6775 | G6: 7049 | H6: 4972 | I6: 7013 | J6: 4354 | K6: 8485 | M6: =SUM(B3,B9,B10) -> 2384
A7: Loans Advances | B7: 0 | C7: 0 | D7: 0 | E7: 0 | F7: 0 | G7: 0 | H7: 0 | I7: 0 | J7: 0 | K7: 0
A8: Other WC items | B8: -4241 | C8: 0 | D8: 0 | E8: 0 | F8: 0 | G8: 0 | H8: 0 | I8: 0 | J8: 0 | K8: -17170
A9: Working capital changes | B9: -3238 | C9: -5724 | D9: -6813 | E9: -12522 | F9: -6974 | G9: 12171 | H9: 293 | I9: -19941 | J9: -19175 | K9: -14113
A10: Direct taxes | B10: -1973 | C10: -2005 | D10: -2664 | E10: -2937 | F10: -2257 | G10: -1850 | H10: -1560 | I10: -2775 | J10: -3996 | K10: -4761
A11: Cash from Investing Activity - | B11: -5506 | C11: -5875 | D11: -5467 | E11: -7174 | F11: -6870 | G11: -19686 | H11: -3252 | I11: -8866 | J11: -5615 | K11: -18626
A12: Fixed assets purchased | B12: -4172 | C12: -5026 | D12: -5906 | E12: -7340 | F12: -6896 | G12: -5989 | H12: -6040 | I12: -6305 | J12: -9946 | K12: -10392
A13: Fixed assets sold | B13: 59 | C13: 63 | D13: 115 | E13: 142 | F13: 102 | G13: 1364 | H13: 120 | I13: 138 | J13: 273 | K13: 583
A14: Investments purchased | B14: -87898 | C14: -132173 | D14: -155159 | E14: -196474 | F14: -198568 | G14: -120055 | H14: -65421 | I14: -50165 | J14: -49927 | K14: -90595
A15: Investments sold | B15: 86436 | C15: 130940 | D15: 154631 | E15: 195898 | F15: 198132 | G15: 111749 | H15: 65127 | I15: 46269 | J15: 50919 | K15: 85634
A16: Interest received | B16: 311 | C16: 346 | D16: 254 | E16: 314 | F16: 372 | G16: 431 | H16: 420 | I16: 464 | J16: 703 | K16: 884
A17: Dividends received | B17: 208 | C17: 409 | D17: 316 | E17: 466 | F17: 722 | G17: 577 | H17: 1247 | I17: 1397 | J17: 1213 | K17: 1374
A18: Investment in group cos | B18: -147 | C18: -647 | D18: -704 | E18: -319 | F18: -418 | G18: -359 | H18: -222 | I18: -62 | J18: -249 | K18: -29
... A32: Net Cash Flow | B32: -154 | C32: 416 | D32: 1529 | E32: 1672 | F32: -1394 | G32: -1370 | H32: 113 | I32: 6 | J32: 1037 | K32: 384

Sheet FS Analysis
B2: ="Historical Financial Statement - "&'Data Sheet'!B1:C1&"(In Crores)" -> Historical Financial Statement - AVENUE SUPERMARTS LTD(In Crores)
B3: Years | C3: ='Data Sheet'!B16 -> 42460 | D3: ='Data Sheet'!C16 -> 42825 | E3: ='Data Sheet'!D16 -> 43190 | F3: ='Data Sheet'!E16 -> 43555 | G3: ='Data Sheet'!F16 -> 43921 | H3: ='Data Sheet'!G16 -> 44286 | I3: ='Data Sheet'!H16 -> 44651 | J3: ='Data Sheet'!I16 -> 45016 | ... L3: ='Data Sheet'!K16 -> 45747
A4: # | B4: Income Statement
B5: Sales | C5: =IFERROR('Data Sheet'!B17,0) -> 8583.76 | D5: =IFERROR('Data Sheet'!C17,0) -> 11897.7 | E5: =IFERROR('Data Sheet'!D17,0) -> 15033.2 | F5: =IFERROR('Data Sheet'!E17,0) -> 20004.52 | G5: =IFERROR('Data Sheet'!F17,0) -> 24870.2 | H5: =IFERROR('Data Sheet'!G17,0) -> 24143.06 | I5: =IFERROR('Data Sheet'!H17,0) -> 30976.27 | J5: =IFERROR('Data Sheet'!I17,0) -> 42839.56 | ... L5: =IFERROR('Data Sheet'!K17,0) -> 59358.05
B6: Sales Growth | C6: - | D6: =IFERROR(D5/C5-1,0) -> 0.38607091 | E6: =IFERROR(E5/D5-1,0) -> 0.26353833 | F6: =IFERROR(F5/E5-1,0) -> 0.33068941 | G6: =IFERROR(G5/F5-1,0) -> 0.24322903 | H6: =IFERROR(H5/G5-1,0) -> -0.029237401 | I6: =IFERROR(I5/H5-1,0) -> 0.28302999 | J6: =IFERROR(J5/I5-1,0) -> 0.38297994 | K6: =IFERROR(K5/J5-1,0) -> 0.1855591 | L6: =IFERROR(L5/K5-1,0) -> 0.16872253
B8: COGS | C8: =IFERROR(SUM('Data Sheet'!B18,'Data Sheet'!B20,'Data Sheet'!B22,'Data Sheet'!B21)-'Data Sheet'!B19,0) -> 7773.18 | D8: =IFERROR(SUM('Data Sheet'!C18,'Data Sheet'!C20,'Data Sheet'!C22,'Data Sheet'!C21)-'Data Sheet'!C19,0) -> 10706.01 | E8: =IFERROR(SUM('Data Sheet'!D18,'Data Sheet'!D20,'Data Sheet'!D22,'Data Sheet'!D21)-'Data Sheet'!D19,0) -> 13413.76 | F8: =IFERROR(SUM('Data Sheet'!E18,'Data Sheet'!E20,'Data Sheet'!E22,'Data Sheet'!E21)-'Data Sheet'!E19,0) -> 18009.53 | G8: =IFERROR(SUM('Data Sheet'!F18,'Data Sheet'!F20,'Data Sheet'!F22,'Data Sheet'!F21)-'Data Sheet'!F19,0) -> 22394.27 | H8: =IFERROR(SUM('Data Sheet'!G18,'Data Sheet'!G20,'Data Sheet'!G22,'Data Sheet'!G21)-'Data Sheet'!G19,0) -> 22012.89 | I8: =IFERROR(SUM('Data Sheet'!H18,'Data Sheet'!H20,'Data Sheet'!H22,'Data Sheet'!H21)-'Data Sheet'!H19,0) -> 28028.46 | J8: =IFERROR(SUM('Data Sheet'!I18,'Data Sheet'!I20,'Data Sheet'!I22,'Data Sheet'!I21)-'Data Sheet'!I19,0) -> 38563.29 | ... L8: =IFERROR(SUM('Data Sheet'!K18,'Data Sheet'!K20,'Data Sheet'!K22,'Data Sheet'!K21)-'Data Sheet'!K19,0) -> 51717.6
B9: COGS % Sales | C9: =IFERROR(C8/C5,0) -> 0.90556819 | D9: =IFERROR(D8/D5,0) -> 0.89983862 | E9: =IFERROR(E8/E5,0) -> 0.89227576 | F9: =IFERROR(F8/F5,0) -> 0.90027304 | G9: =IFERROR(G8/G5,0) -> 0.90044592 | H9: =IFERROR(H8/H5,0) -> 0.91176885 | I9: =IFERROR(I8/I5,0) -> 0.90483651 | J9: =IFERROR(J8/J5,0) -> 0.90017941 | ... L9: =IFERROR(L8/L5,0) -> 0.87128199
B11: Gross Profit | C11: =IFERROR(C5-C8,0) -> 810.58 | D11: =IFERROR(D5-D8,0) -> 1191.69 | E11: =IFERROR(E5-E8,0) -> 1619.44 | F11: =IFERROR(F5-F8,0) -> 1994.99 | G11: =IFERROR(G5-G8,0) -> 2475.93 | H11: =IFERROR(H5-H8,0) -> 2130.17 | I11: =IFERROR(I5-I8,0) -> 2947.81 | J11: =IFERROR(J5-J8,0) -> 4276.27 | ... L11: =IFERROR(L5-L8,0) -> 7640.45
B12: Gross Margins | C12: =IFERROR(C11/C5,0) -> 0.094431811 | D12: =IFERROR(D11/D5,0) -> 0.10016138 | E12: =IFERROR(E11/E5,0) -> 0.10772424 | F12: =IFERROR(F11/F5,0) -> 0.099726962 | G12: =IFERROR(G11/G5,0) -> 0.099554085 | H12: =IFERROR(H11/H5,0) -> 0.088231152 | I12: =IFERROR(I11/I5,0) -> 0.095163491 | J12: =IFERROR(J11/J5,0) -> 0.099820586 | ... L12: =IFERROR(L11/L5,0) -> 0.12871801
B14: Selling & General Expenses | C14: =IFERROR(SUM('Data Sheet'!B23:B24)-'Data Sheet'!B25,0) -> 129.1 | D14: =IFERROR(SUM('Data Sheet'!C23:C24)-'Data Sheet'!C25,0) -> 194.81 | E14: =IFERROR(SUM('Data Sheet'!D23:D24)-'Data Sheet'!D25,0) -> 178.83 | F14: =IFERROR(SUM('Data Sheet'!E23:E24)-'Data Sheet'!E25,0) -> 313.35 | G14: =IFERROR(SUM('Data Sheet'!F23:F24)-'Data Sheet'!F25,0) -> 287.63 | H14: =IFERROR(SUM('Data Sheet'!G23:G24)-'Data Sheet'!G25,0) -> 190.91 | I14: =IFERROR(SUM('Data Sheet'!H23:H24)-'Data Sheet'!H25,0) -> 331.82 | J14: =IFERROR(SUM('Data Sheet'!I23:I24)-'Data Sheet'!I25,0) -> 509.9 | ... L14: =IFERROR(SUM('Data Sheet'!K23:K24)-'Data Sheet'!K25,0) -> 3028.81
B15: S&G Exp % Sales | C15: =IFERROR(C14/C5,0) -> 0.015040029 | D15: =IFERROR(D14/D5,0) -> 0.016373753 | E15: =IFERROR(E14/E5,0) -> 0.011895671 | F15: =IFERROR(F14/F5,0) -> 0.01566396 | G15: =IFERROR(G14/G5,0) -> 0.011565247 | H15: =IFERROR(H14/H5,0) -> 0.0079074484 | I15: =IFERROR(I14/I5,0) -> 0.010712071 | J15: =IFERROR(J14/J5,0) -> 0.01190255 | ... L15: =IFERROR(L14/L5,0) -> 0.051026103
B17: EBITDA | C17: =IFERROR(C11-C14,0) -> 681.48 | D17: =IFERROR(D11-D14,0) -> 996.88 | E17: =IFERROR(E11-E14,0) -> 1440.61 | F17: =IFERROR(F11-F14,0) -> 1681.64 | G17: =IFERROR(G11-G14,0) -> 2188.3 | H17: =IFERROR(H11-H14,0) -> 1939.26 | I17: =IFERROR(I11-I14,0) -> 2615.99 | J17: =IFERROR(J11-J14,0) -> 3766.37 | ... L17: =IFERROR(L11-L14,0) -> 4611.64
B18: EBITDA Margins | C18: =IFERROR(C17/C5,0) -> 0.079391782 | D18: =IFERROR(D17/D5,0) -> 0.083787623 | E18: =IFERROR(E17/E5,0) -> 0.095828566 | F18: =IFERROR(F17/F5,0) -> 0.084063002 | G18: =IFERROR(G17/G5,0) -> 0.087988838 | H18: =IFERROR(H17/H5,0) -> 0.080323704 | I18: =IFERROR(I17/I5,0) -> 0.08445142 | J18: =IFERROR(J17/J5,0) -> 0.087918037 | ... L18: =IFERROR(L17/L5,0) -> 0.077691905
B20: Interest | C20: =IFERROR('Data Sheet'!B27,0) -> 91.34 | D20: =IFERROR('Data Sheet'!C27,0) -> 121.98 | E20: =IFERROR('Data Sheet'!D27,0) -> 59.54 | F20: =IFERROR('Data Sheet'!E27,0) -> 47.21 | G20: =IFERROR('Data Sheet'!F27,0) -> 69.12 | H20: =IFERROR('Data Sheet'!G27,0) -> 41.65 | I20: =IFERROR('Data Sheet'!H27,0) -> 53.79 | J20: =IFERROR('Data Sheet'!I27,0) -> 67.41 | ... L20: =IFERROR('Data Sheet'!K27,0) -> 69.45
B21: Interest % Sales | C21: =IFERROR(C20/C5,0) -> 0.010641024 | D21: =IFERROR(D20/D5,0) -> 0.010252402 | E21: =IFERROR(E20/E5,0) -> 0.0039605673 | F21: =IFERROR(F20/F5,0) -> 0.0023599666 | G21: =IFERROR(G20/G5,0) -> 0.0027792298 | H21: =IFERROR(H20/H5,0) -> 0.0017251334 | I21: =IFERROR(I20/I5,0) -> 0.0017364905 | J21: =IFERROR(J20/J5,0) -> 0.0015735456 | ... L21: =IFERROR(L20/L5,0) -> 0.0011700182
B23: Depreciation | C23: =IFERROR('Data Sheet'!B26,0) -> 98.43 | D23: =IFERROR('Data Sheet'!C26,0) -> 127.82 | E23: =IFERROR('Data Sheet'!D26,0) -> 159 | F23: =IFERROR('Data Sheet'!E26,0) -> 212.49 | G23: =IFERROR('Data Sheet'!F26,0) -> 374.41 | H23: =IFERROR('Data Sheet'!G26,0) -> 414.16 | I23: =IFERROR('Data Sheet'!H26,0) -> 498.08 | J23: =IFERROR('Data Sheet'!I26,0) -> 638.87 | ... L23: =IFERROR('Data Sheet'!K26,0) -> 869.52
B24: Depreciation%Sales | C24: =IFERROR(C23/C5,0) -> 0.011467003 | D24: =IFERROR(D23/D5,0) -> 0.010743253 | E24: =IFERROR(E23/E5,0) -> 0.01057659 | F24: =IFERROR(F23/F5,0) -> 0.010622099 | G24: =IFERROR(G23/G5,0) -> 0.015054563 | H24: =IFERROR(H23/H5,0) -> 0.017154412 | I24: =IFERROR(I23/I5,0) -> 0.016079405 | J24: =IFERROR(J23/J5,0) -> 0.014913085 | ... L24: =IFERROR(L23/L5,0) -> 0.014648729
B26: Earnings Before Tax | C26: =IFERROR(C17-SUM(C20,C23),0) -> 491.71 | D26: =IFERROR(D17-SUM(D20,D23),0) -> 747.08 | E26: =IFERROR(E17-SUM(E20,E23),0) -> 1222.07 | F26: =IFERROR(F17-SUM(F20,F23),0) -> 1421.94 | G26: =IFERROR(G17-SUM(G20,G23),0) -> 1744.77 | H26: =IFERROR(H17-SUM(H20,H23),0) -> 1483.45 | I26: =IFERROR(I17-SUM(I20,I23),0) -> 2064.12 | J26: =IFERROR(J17-SUM(J20,J23),0) -> 3060.09 | ... L26: =IFERROR(L17-SUM(L20,L23),0) -> 3672.67
B27: EBT % Sales | C27: =IFERROR(C26/C5,0) -> 0.057283754 | D27: =IFERROR(D26/D5,0) -> 0.062791968 | E27: =IFERROR(E26/E5,0) -> 0.081291408 | F27: =IFERROR(F26/F5,0) -> 0.071080936 | G27: =IFERROR(G26/G5,0) -> 0.070155045 | H27: =IFERROR(H26/H5,0) -> 0.061444158 | I27: =IFERROR(I26/I5,0) -> 0.066635525 | J27: =IFERROR(J26/J5,0) -> 0.071431406 | ... L27: =IFERROR(L26/L5,0) -> 0.061873158
B29: Tax | C29: =IFERROR('Data Sheet'!B29,0) -> 171.47 | D29: =IFERROR('Data Sheet'!C29,0) -> 268.28 | E29: =IFERROR('Data Sheet'!D29,0) -> 415.79 | F29: =IFERROR('Data Sheet'!E29,0) -> 519.48 | G29: =IFERROR('Data Sheet'!F29,0) -> 443.79 | H29: =IFERROR('Data Sheet'!G29,0) -> 384.02 | I29: =IFERROR('Data Sheet'!H29,0) -> 571.72 | J29: =IFERROR('Data Sheet'!I29,0) -> 681.75 | ... L29: =IFERROR('Data Sheet'!K29,0) -> 965.22
B30: Effective Tax Rate | C30: =IFERROR(C29/C26,0) -> 0.34872181 | D30: =IFERROR(D29/D26,0) -> 0.35910478 | E30: =IFERROR(E29/E26,0) -> 0.34023419 | F30: =IFERROR(F29/F26,0) -> 0.36533187 | G30: =IFERROR(G29/G26,0) -> 0.25435444 | H30: =IFERROR(H29/H26,0) -> 0.25886953 | I30: =IFERROR(I29/I26,0) -> 0.27698002 | J30: =IFERROR(J29/J26,0) -> 0.22278757 | ... L30: =IFERROR(L29/L26,0) -> 0.26281152
B32: Net Profit | C32: =IFERROR('Data Sheet'!B30,0) -> 320.24 | D32: =IFERROR('Data Sheet'!C30,0) -> 478.75 | E32: =IFERROR('Data Sheet'!D30,0) -> 806.26 | F32: =IFERROR('Data Sheet'!E30,0) -> 902.54 | G32: =IFERROR('Data Sheet'!F30,0) -> 1301.08 | H32: =IFERROR('Data Sheet'!G30,0) -> 1099.49 | I32: =IFERROR('Data Sheet'!H30,0) -> 1492.55 | J32: =IFERROR('Data Sheet'!I30,0) -> 2378.51 | ... L32: =IFERROR('Data Sheet'!K30,0) -> 2708.02
B33: Net Margins | C33: =IFERROR(C32/C5,0) -> 0.03730766 | D33: =IFERROR(D32/D5,0) -> 0.04023887 | E33: =IFERROR(E32/E5,0) -> 0.053631961 | F33: =IFERROR(F32/F5,0) -> 0.045116804 | G33: =IFERROR(G32/G5,0) -> 0.052314819 | H33: =IFERROR(H32/H5,0) -> 0.045540623 | I33: =IFERROR(I32/I5,0) -> 0.048183658 | J33: =IFERROR(J32/J5,0) -> 0.055521345 | ... L33: =IFERROR(L32/L5,0) -> 0.045621782
B35: No of Equity Shares | C35: =IFERROR('Data Sheet'!B93,0) -> 56.15 | D35: =IFERROR('Data Sheet'!C93,0) -> 62.41 | E35: =IFERROR('Data Sheet'!D93,0) -> 62.41 | F35: =IFERROR('Data Sheet'!E93,0) -> 62.41 | G35: =IFERROR('Data Sheet'!F93,0) -> 64.78 | H35: =IFERROR('Data Sheet'!G93,0) -> 64.78 | I35: =IFERROR('Data Sheet'!H93,0) -> 64.78 | J35: =IFERROR('Data Sheet'!I93,0) -> 64.83 | ... L35: =IFERROR('Data Sheet'!K93,0) -> 65.07
B37: Earnings per Share | C37: =IFERROR(C32/C35,0) -> 5.7032947 | D37: =IFERROR(D32/D35,0) -> 7.6710463 | E37: =IFERROR(E32/E35,0) -> 12.918763 | F37: =IFERROR(F32/F35,0) -> 14.461465 | G37: =IFERROR(G32/G35,0) -> 20.084594 | H37: =IFERROR(H32/H35,0) -> 16.972677 | I37: =IFERROR(I32/I35,0) -> 23.04029 | J37: =IFERROR(J32/J35,0) -> 36.688416 | ... L37: =IFERROR(L32/L35,0) -> 41.617028
B38: EPS Growth % | C38: - | D38: =IFERROR(D37/C37-1,0) -> 0.34502014 | E38: =IFERROR(E37/D37-1,0) -> 0.68409399 | F38: =IFERROR(F37/E37-1,0) -> 0.11941557 | G38: =IFERROR(G37/F37-1,0) -> 0.38883541 | H38: =IFERROR(H37/G37-1,0) -> -0.15494051 | I38: =IFERROR(I37/H37-1,0) -> 0.35749302 | J38: =IFERROR(J37/I37-1,0) -> 0.5923591 | K38: =IFERROR(K37/J37-1,0) -> 0.062352378 | L38: =IFERROR(L37/K37-1,0) -> 0.067759653
B40: Dividend per Share | C40: =IFERROR('Data Sheet'!B31/'FS Analysis'!C35,0) -> 0 | D40: =IFERROR('Data Sheet'!C31/'FS Analysis'!D35,0) -> 0 | E40: =IFERROR('Data Sheet'!D31/'FS Analysis'!E35,0) -> 0 | F40: =IFERROR('Data Sheet'!E31/'FS Analysis'!F35,0) -> 0 | G40: =IFERROR('Data Sheet'!F31/'FS Analysis'!G35,0) -> 0 | H40: =IFERROR('Data Sheet'!G31/'FS Analysis'!H35,0) -> 0 | I40: =IFERROR('Data Sheet'!H31/'FS Analysis'!I35,0) -> 0 | J40: =IFERROR('Data Sheet'!I31/'FS Analysis'!J35,0) -> 0 | ... L40: =IFERROR('Data Sheet'!K31/'FS Analysis'!L35,0) -> 0
B41: Dividend payout ratio | C41: =IFERROR(C40/C37,0) -> 0 | D41: =IFERROR(D40/D37,0) -> 0 | E41: =IFERROR(E40/E37,0) -> 0 | F41: =IFERROR(F40/F37,0) -> 0 | G41: =IFERROR(G40/G37,0) -> 0 | H41: =IFERROR(H40/H37,0) -> 0 | I41: =IFERROR(I40/I37,0) -> 0 | J41: =IFERROR(J40/J37,0) -> 0 | ... L41: =IFERROR(L40/L37,0) -> 0
B43: Retained Earnings | C43: =IFERROR(IF(C37>C40,1-C41,0),0) -> 1 | D43: =IFERROR(IF(D37>D40,1-D41,0),0) -> 1 | E43: =IFERROR(IF(E37>E40,1-E41,0),0) -> 1 | F43: =IFERROR(IF(F37>F40,1-F41,0),0) -> 1 | G43: =IFERROR(IF(G37>G40,1-G41,0),0) -> 1 | H43: =IFERROR(IF(H37>H40,1-H41,0),0) -> 1 | I43: =IFERROR(IF(I37>I40,1-I41,0),0) -> 1 | J43: =IFERROR(IF(J37>J40,1-J41,0),0) -> 1 | ... L43: =IFERROR(IF(L37>L40,1-L41,0),0) -> 1
A45: # | B45: Balance Sheet
B46: =IFERROR('Data Sheet'!A57,0) -> Equity Share Capital | C46: =IFERROR('Data Sheet'!B57,0) -> 561.54 | D46: =IFERROR('Data Sheet'!C57,0) -> 624.08 | E46: =IFERROR('Data Sheet'!D57,0) -> 624.08 | F46: =IFERROR('Data Sheet'!E57,0) -> 624.08 | G46: =IFERROR('Data Sheet'!F57,0) -> 647.77 | H46: =IFERROR('Data Sheet'!G57,0) -> 647.77 | I46: =IFERROR('Data Sheet'!H57,0) -> 647.77 | ... L46: =IFERROR('Data Sheet'!K57,0) -> 650.73
B47: =IFERROR('Data Sheet'!A58,0) -> Reserves | C47: =IFERROR('Data Sheet'!B58,0) -> 958.9 | D47: =IFERROR('Data Sheet'!C58,0) -> 3217.7 | E47: =IFERROR('Data Sheet'!D58,0) -> 4044.97 | F47: =IFERROR('Data Sheet'!E58,0) -> 4963.37 | G47: =IFERROR('Data Sheet'!F58,0) -> 10431.97 | H47: =IFERROR('Data Sheet'!G58,0) -> 11535.94 | I47: =IFERROR('Data Sheet'!H58,0) -> 13029.87 | ... L47: =IFERROR('Data Sheet'!K58,0) -> 20777.02
B48: =IFERROR('Data Sheet'!A59,0) -> Borrowings | C48: =IFERROR('Data Sheet'!B59,0) -> 1192.34 | D48: =IFERROR('Data Sheet'!C59,0) -> 1497.32 | E48: =IFERROR('Data Sheet'!D59,0) -> 439.25 | F48: =IFERROR('Data Sheet'!E59,0) -> 700.15 | G48: =IFERROR('Data Sheet'!F59,0) -> 333.19 | H48: =IFERROR('Data Sheet'!G59,0) -> 392.71 | I48: =IFERROR('Data Sheet'!H59,0) -> 646.94 | ... L48: =IFERROR('Data Sheet'!K59,0) -> 819.62
B49: =IFERROR('Data Sheet'!A60,0) -> Other Liabilities | C49: =IFERROR('Data Sheet'!B60,0) -> 388.78 | D49: =IFERROR('Data Sheet'!C60,0) -> 480.18 | E49: =IFERROR('Data Sheet'!D60,0) -> 539.92 | F49: =IFERROR('Data Sheet'!E60,0) -> 717.9 | G49: =IFERROR('Data Sheet'!F60,0) -> 663.23 | H49: =IFERROR('Data Sheet'!G60,0) -> 1078.63 | I49: =IFERROR('Data Sheet'!H60,0) -> 1146.4 | ... L49: =IFERROR('Data Sheet'!K60,0) -> 2072.92
B50: Total Liabilties | C50: =IFERROR('Data Sheet'!B61,0) -> 3101.56 | D50: =IFERROR('Data Sheet'!C61,0) -> 5819.28 | E50: =IFERROR('Data Sheet'!D61,0) -> 5648.22 | F50: =IFERROR('Data Sheet'!E61,0) -> 7005.5 | G50: =IFERROR('Data Sheet'!F61,0) -> 12076.16 | H50: =IFERROR('Data Sheet'!G61,0) -> 13655.05 | I50: =IFERROR('Data Sheet'!H61,0) -> 15470.98 | J50: =IFERROR('Data Sheet'!I61,0) -> 18104.52 | ... L50: =IFERROR('Data Sheet'!K61,0) -> 24320.29
B52: =IFERROR('Data Sheet'!A62,0) -> Net Block | C52: =IFERROR('Data Sheet'!B62,0) -> 2093.52 | D52: =IFERROR('Data Sheet'!C62,0) -> 2577.75 | E52: =IFERROR('Data Sheet'!D62,0) -> 3399.97 | F52: =IFERROR('Data Sheet'!E62,0) -> 4400.37 | G52: =IFERROR('Data Sheet'!F62,0) -> 5948.03 | H52: =IFERROR('Data Sheet'!G62,0) -> 7008.8 | I52: =IFERROR('Data Sheet'!H62,0) -> 9260.02 | ... L52: =IFERROR('Data Sheet'!K62,0) -> 16206.46
B53: =IFERROR('Data Sheet'!A63,0) -> Capital Work in Progress | C53: =IFERROR('Data Sheet'!B63,0) -> 81.69 | D53: =IFERROR('Data Sheet'!C63,0) -> 152.89 | E53: =IFERROR('Data Sheet'!D63,0) -> 147.07 | F53: =IFERROR('Data Sheet'!E63,0) -> 376.84 | G53: =IFERROR('Data Sheet'!F63,0) -> 364.4 | H53: =IFERROR('Data Sheet'!G63,0) -> 1019.59 | I53: =IFERROR('Data Sheet'!H63,0) -> 1129.34 | ... L53: =IFERROR('Data Sheet'!K63,0) -> 1099.35
B54: =IFERROR('Data Sheet'!A64,0) -> Investments | C54: =IFERROR('Data Sheet'!B64,0) -> 29.33 | D54: =IFERROR('Data Sheet'!C64,0) -> 25.69 | E54: =IFERROR('Data Sheet'!D64,0) -> 68.18 | F54: =IFERROR('Data Sheet'!E64,0) -> 16.53 | G54: =IFERROR('Data Sheet'!F64,0) -> 14.68 | H54: =IFERROR('Data Sheet'!G64,0) -> 2.95 | I54: =IFERROR('Data Sheet'!H64,0) -> 5.94 | ... L54: =IFERROR('Data Sheet'!K64,0) -> 3.26
B55: =IFERROR('Data Sheet'!A65,0) -> Other Assets | C55: =IFERROR('Data Sheet'!B65-SUM('Data Sheet'!B67:B69),0) -> 181.81 | D55: =IFERROR('Data Sheet'!C65-SUM('Data Sheet'!C67:C69),0) -> 209.76 | E55: =IFERROR('Data Sheet'!D65-SUM('Data Sheet'!D67:D69),0) -> 275.85 | F55: =IFERROR('Data Sheet'!E65-SUM('Data Sheet'!E67:E69),0) -> 319.67 | G55: =IFERROR('Data Sheet'!F65-SUM('Data Sheet'!F67:F69),0) -> 3674.22 | H55: =IFERROR('Data Sheet'!G65-SUM('Data Sheet'!G67:G69),0) -> 1886.27 | I55: =IFERROR('Data Sheet'!H65-SUM('Data Sheet'!H67:H69),0) -> 1967.55 | J55: =IFERROR('Data Sheet'!I65-SUM('Data Sheet'!I67:I69),0) -> 1018.71 | ... L55: =IFERROR('Data Sheet'!K65-SUM('Data Sheet'!K67:K69),0) -> 1454.86
B56: Total Non-Current Assets | C56: =IFERROR(SUM(C52:C55),0) -> 2386.35 | D56: =IFERROR(SUM(D52:D55),0) -> 2966.09 | E56: =IFERROR(SUM(E52:E55),0) -> 3891.07 | F56: =IFERROR(SUM(F52:F55),0) -> 5113.41 | G56: =IFERROR(SUM(G52:G55),0) -> 10001.33 | H56: =IFERROR(SUM(H52:H55),0) -> 9917.61 | I56: =IFERROR(SUM(I52:I55),0) -> 12362.85 | J56: =IFERROR(SUM(J52:J55),0) -> 13390.55 | ... L56: =IFERROR(SUM(L52:L55),0) -> 18763.93
B58: =IFERROR('Data Sheet'!A67,0) -> Receivables | C58: =IFERROR('Data Sheet'!B67,0) -> 8.42 | D58: =IFERROR('Data Sheet'!C67,0) -> 21 | E58: =IFERROR('Data Sheet'!D67,0) -> 33.52 | F58: =IFERROR('Data Sheet'!E67,0) -> 64.37 | G58: =IFERROR('Data Sheet'!F67,0) -> 19.55 | H58: =IFERROR('Data Sheet'!G67,0) -> 43.58 | I58: =IFERROR('Data Sheet'!H67,0) -> 66.89 | ... L58: =IFERROR('Data Sheet'!K67,0) -> 153.79
B59: =IFERROR('Data Sheet'!A68,0) -> Inventory | C59: =IFERROR('Data Sheet'!B68,0) -> 671.69 | D59: =IFERROR('Data Sheet'!C68,0) -> 947.9 | E59: =IFERROR('Data Sheet'!D68,0) -> 1163.45 | F59: =IFERROR('Data Sheet'!E68,0) -> 1608.65 | G59: =IFERROR('Data Sheet'!F68,0) -> 1947.4 | H59: =IFERROR('Data Sheet'!G68,0) -> 2248.28 | I59: =IFERROR('Data Sheet'!H68,0) -> 2742.66 | ... L59: =IFERROR('Data Sheet'!K68,0) -> 5044.37
B60: =IFERROR('Data Sheet'!A69,0) -> Cash & Bank | C60: =IFERROR('Data Sheet'!B69,0) -> 35.1 | D60: =IFERROR('Data Sheet'!C69,0) -> 1884.29 | E60: =IFERROR('Data Sheet'!D69,0) -> 560.18 | F60: =IFERROR('Data Sheet'!E69,0) -> 219.07 | G60: =IFERROR('Data Sheet'!F69,0) -> 107.88 | H60: =IFERROR('Data Sheet'!G69,0) -> 1445.58 | I60: =IFERROR('Data Sheet'!H69,0) -> 298.58 | ... L60: =IFERROR('Data Sheet'!K69,0) -> 358.2
B61: Total Current Assets | C61: =IFERROR(SUM(C58:C60),0) -> 715.21 | D61: =IFERROR(SUM(D58:D60),0) -> 2853.19 | E61: =IFERROR(SUM(E58:E60),0) -> 1757.15 | F61: =IFERROR(SUM(F58:F60),0) -> 1892.09 | G61: =IFERROR(SUM(G58:G60),0) -> 2074.83 | H61: =IFERROR(SUM(H58:H60),0) -> 3737.44 | I61: =IFERROR(SUM(I58:I60),0) -> 3108.13 | J61: =IFERROR(SUM(J58:J60),0) -> 4713.97 | ... L61: =IFERROR(SUM(L58:L60),0) -> 5556.36
B63: Total Assets | C63: =IFERROR(SUM(C56,C61),0) -> 3101.56 | D63: =IFERROR(SUM(D56,D61),0) -> 5819.28 | E63: =IFERROR(SUM(E56,E61),0) -> 5648.22 | F63: =IFERROR(SUM(F56,F61),0) -> 7005.5 | G63: =IFERROR(SUM(G56,G61),0) -> 12076.16 | H63: =IFERROR(SUM(H56,H61),0) -> 13655.05 | I63: =IFERROR(SUM(I56,I61),0) -> 15470.98 | J63: =IFERROR(SUM(J56,J61),0) -> 18104.52 | ... L63: =IFERROR(SUM(L56,L61),0) -> 24320.29
B65: Check | C65: =IFERROR(IF(C50=C63,TRUE,FALSE),0) -> TRUE | D65: =IFERROR(IF(D50=D63,TRUE,FALSE),0) -> TRUE | E65: =IFERROR(IF(E50=E63,TRUE,FALSE),0) -> TRUE | F65: =IFERROR(IF(F50=F63,TRUE,FALSE),0) -> TRUE | G65: =IFERROR(IF(G50=G63,TRUE,FALSE),0) -> TRUE | H65: =IFERROR(IF(H50=H63,TRUE,FALSE),0) -> TRUE | I65: =IFERROR(IF(I50=I63,TRUE,FALSE),0) -> TRUE | J65: =IFERROR(IF(J50=J63,TRUE,FALSE),0) -> TRUE | ... L65: =IFERROR(IF(L50=L63,TRUE,FALSE),0) -> TRUE
A67: # | B67: Cash Flow Statements
B68: Operating Activities
B69: =IFERROR('Cash Flow Data'!A3,0) -> Profit from operations | C69: =IFERROR('Cash Flow Data'!B3,0) -> 7595 | D69: =IFERROR('Cash Flow Data'!C3,0) -> 7911 | E69: =IFERROR('Cash Flow Data'!D3,0) -> 10159 | F69: =IFERROR('Cash Flow Data'!E3,0) -> 11112 | G69: =IFERROR('Cash Flow Data'!F3,0) -> 7774 | H69: =IFERROR('Cash Flow Data'!G3,0) -> 7588 | I69: =IFERROR('Cash Flow Data'!H3,0) -> 10515 | ... L69: =IFERROR('Cash Flow Data'!K3,0) -> 22050
B70: =IFERROR('Cash Flow Data'!A4,0) -> Receivables | C70: =IFERROR('Cash Flow Data'!B4,0) -> 177 | D70: =IFERROR('Cash Flow Data'!C4,0) -> -8609 | E70: =IFERROR('Cash Flow Data'!D4,0) -> -11918 | F70: =IFERROR('Cash Flow Data'!E4,0) -> -13712 | G70: =IFERROR('Cash Flow Data'!F4,0) -> -1516 | H70: =IFERROR('Cash Flow Data'!G4,0) -> 4896 | I70: =IFERROR('Cash Flow Data'!H4,0) -> -2506 | ... L70: =IFERROR('Cash Flow Data'!K4,0) -> -3782
B71: =IFERROR('Cash Flow Data'!A5,0) -> Inventory | C71: =IFERROR('Cash Flow Data'!B5,0) -> -1113 | D71: =IFERROR('Cash Flow Data'!C5,0) -> 241 | E71: =IFERROR('Cash Flow Data'!D5,0) -> -256 | F71: =IFERROR('Cash Flow Data'!E5,0) -> -2276 | G71: =IFERROR('Cash Flow Data'!F5,0) -> 1316 | H71: =IFERROR('Cash Flow Data'!G5,0) -> 226 | I71: =IFERROR('Cash Flow Data'!H5,0) -> -2173 | ... L71: =IFERROR('Cash Flow Data'!K5,0) -> -1646
B72: =IFERROR('Cash Flow Data'!A6,0) -> Payables | C72: =IFERROR('Cash Flow Data'!B6,0) -> 1939 | D72: =IFERROR('Cash Flow Data'!C6,0) -> 2645 | E72: =IFERROR('Cash Flow Data'!D6,0) -> 5361 | F72: =IFERROR('Cash Flow Data'!E6,0) -> 3466 | G72: =IFERROR('Cash Flow Data'!F6,0) -> -6775 | H72: =IFERROR('Cash Flow Data'!G6,0) -> 7049 | I72: =IFERROR('Cash Flow Data'!H6,0) -> 4972 | ... L72: =IFERROR('Cash Flow Data'!K6,0) -> 8485
B73: =IFERROR('Cash Flow Data'!A7,0) -> Loans Advances | C73: =IFERROR('Cash Flow Data'!B7,0) -> 0 | D73: =IFERROR('Cash Flow Data'!C7,0) -> 0 | E73: =IFERROR('Cash Flow Data'!D7,0) -> 0 | F73: =IFERROR('Cash Flow Data'!E7,0) -> 0 | G73: =IFERROR('Cash Flow Data'!F7,0) -> 0 | H73: =IFERROR('Cash Flow Data'!G7,0) -> 0 | I73: =IFERROR('Cash Flow Data'!H7,0) -> 0 | ... L73: =IFERROR('Cash Flow Data'!K7,0) -> 0
B74: =IFERROR('Cash Flow Data'!A8,0) -> Other WC items | C74: =IFERROR('Cash Flow Data'!B8,0) -> -4241 | D74: =IFERROR('Cash Flow Data'!C8,0) -> 0 | E74: =IFERROR('Cash Flow Data'!D8,0) -> 0 | F74: =IFERROR('Cash Flow Data'!E8,0) -> 0 | G74: =IFERROR('Cash Flow Data'!F8,0) -> 0 | H74: =IFERROR('Cash Flow Data'!G8,0) -> 0 | I74: =IFERROR('Cash Flow Data'!H8,0) -> 0 | ... L74: =IFERROR('Cash Flow Data'!K8,0) -> -17170
B75: =IFERROR('Cash Flow Data'!A9,0) -> Working capital changes | C75: =IFERROR('Cash Flow Data'!B9,0) -> -3238 | D75: =IFERROR('Cash Flow Data'!C9,0) -> -5724 | E75: =IFERROR('Cash Flow Data'!D9,0) -> -6813 | F75: =IFERROR('Cash Flow Data'!E9,0) -> -12522 | G75: =IFERROR('Cash Flow Data'!F9,0) -> -6974 | H75: =IFERROR('Cash Flow Data'!G9,0) -> 12171 | I75: =IFERROR('Cash Flow Data'!H9,0) -> 293 | ... L75: =IFERROR('Cash Flow Data'!K9,0) -> -14113
B76: =IFERROR('Cash Flow Data'!A10,0) -> Direct taxes | C76: =IFERROR('Cash Flow Data'!B10,0) -> -1973 | D76: =IFERROR('Cash Flow Data'!C10,0) -> -2005 | E76: =IFERROR('Cash Flow Data'!D10,0) -> -2664 | F76: =IFERROR('Cash Flow Data'!E10,0) -> -2937 | G76: =IFERROR('Cash Flow Data'!F10,0) -> -2257 | H76: =IFERROR('Cash Flow Data'!G10,0) -> -1850 | I76: =IFERROR('Cash Flow Data'!H10,0) -> -1560 | ... L76: =IFERROR('Cash Flow Data'!K10,0) -> -4761
B77: Cash from Operating Activity | C77: =IFERROR(SUM(C69,C75,C76),0) -> 2384 | D77: =IFERROR(SUM(D69,D75,D76),0) -> 182 | E77: =IFERROR(SUM(E69,E75,E76),0) -> 682 | F77: =IFERROR(SUM(F69,F75,F76),0) -> -4347 | G77: =IFERROR(SUM(G69,G75,G76),0) -> -1457 | H77: =IFERROR(SUM(H69,H75,H76),0) -> 17909 | I77: =IFERROR(SUM(I69,I75,I76),0) -> 9248 | J77: =IFERROR(SUM(J69,J75,J76),0) -> -7074 | ... L77: =IFERROR(SUM(L69,L75,L76),0) -> 3176
B79: Investing Activities
B80: =IFERROR('Cash Flow Data'!A12,0) -> Fixed assets purchased | C80: =IFERROR('Cash Flow Data'!B12,0) -> -4172 | D80: =IFERROR('Cash Flow Data'!C12,0) -> -5026 | E80: =IFERROR('Cash Flow Data'!D12,0) -> -5906 | F80: =IFERROR('Cash Flow Data'!E12,0) -> -7340 | G80: =IFERROR('Cash Flow Data'!F12,0) -> -6896 | H80: =IFERROR('Cash Flow Data'!G12,0) -> -5989 | I80: =IFERROR('Cash Flow Data'!H12,0) -> -6040 | ... L80: =IFERROR('Cash Flow Data'!K12,0) -> -10392
B81: =IFERROR('Cash Flow Data'!A13,0) -> Fixed assets sold | C81: =IFERROR('Cash Flow Data'!B13,0) -> 59 | D81: =IFERROR('Cash Flow Data'!C13,0) -> 63 | E81: =IFERROR('Cash Flow Data'!D13,0) -> 115 | F81: =IFERROR('Cash Flow Data'!E13,0) -> 142 | G81: =IFERROR('Cash Flow Data'!F13,0) -> 102 | H81: =IFERROR('Cash Flow Data'!G13,0) -> 1364 | I81: =IFERROR('Cash Flow Data'!H13,0) -> 120 | ... L81: =IFERROR('Cash Flow Data'!K13,0) -> 583
B82: =IFERROR('Cash Flow Data'!A14,0) -> Investments purchased | C82: =IFERROR('Cash Flow Data'!B14,0) -> -87898 | D82: =IFERROR('Cash Flow Data'!C14,0) -> -132173 | E82: =IFERROR('Cash Flow Data'!D14,0) -> -155159 | F82: =IFERROR('Cash Flow Data'!E14,0) -> -196474 | G82: =IFERROR('Cash Flow Data'!F14,0) -> -198568 | H82: =IFERROR('Cash Flow Data'!G14,0) -> -120055 | I82: =IFERROR('Cash Flow Data'!H14,0) -> -65421 | ... L82: =IFERROR('Cash Flow Data'!K14,0) -> -90595
B83: =IFERROR('Cash Flow Data'!A15,0) -> Investments sold | C83: =IFERROR('Cash Flow Data'!B15,0) -> 86436 | D83: =IFERROR('Cash Flow Data'!C15,0) -> 130940 | E83: =IFERROR('Cash Flow Data'!D15,0) -> 154631 | F83: =IFERROR('Cash Flow Data'!E15,0) -> 195898 | G83: =IFERROR('Cash Flow Data'!F15,0) -> 198132 | H83: =IFERROR('Cash Flow Data'!G15,0) -> 111749 | I83: =IFERROR('Cash Flow Data'!H15,0) -> 65127 | ... L83: =IFERROR('Cash Flow Data'!K15,0) -> 85634
B84: =IFERROR('Cash Flow Data'!A16,0) -> Interest received | C84: =IFERROR('Cash Flow Data'!B16,0) -> 311 | D84: =IFERROR('Cash Flow Data'!C16,0) -> 346 | E84: =IFERROR('Cash Flow Data'!D16,0) -> 254 | F84: =IFERROR('Cash Flow Data'!E16,0) -> 314 | G84: =IFERROR('Cash Flow Data'!F16,0) -> 372 | H84: =IFERROR('Cash Flow Data'!G16,0) -> 431 | I84: =IFERROR('Cash Flow Data'!H16,0) -> 420 | ... L84: =IFERROR('Cash Flow Data'!K16,0) -> 884
B85: =IFERROR('Cash Flow Data'!A17,0) -> Dividends received | C85: =IFERROR('Cash Flow Data'!B17,0) -> 208 | D85: =IFERROR('Cash Flow Data'!C17,0) -> 409 | E85: =IFERROR('Cash Flow Data'!D17,0) -> 316 | F85: =IFERROR('Cash Flow Data'!E17,0) -> 466 | G85: =IFERROR('Cash Flow Data'!F17,0) -> 722 | H85: =IFERROR('Cash Flow Data'!G17,0) -> 577 | I85: =IFERROR('Cash Flow Data'!H17,0) -> 1247 | ... L85: =IFERROR('Cash Flow Data'!K17,0) -> 1374
B86: =IFERROR('Cash Flow Data'!A18,0) -> Investment in group cos | C86: =IFERROR('Cash Flow Data'!B18,0) -> -147 | D86: =IFERROR('Cash Flow Data'!C18,0) -> -647 | E86: =IFERROR('Cash Flow Data'!D18,0) -> -704 | F86: =IFERROR('Cash Flow Data'!E18,0) -> -319 | G86: =IFERROR('Cash Flow Data'!F18,0) -> -418 | H86: =IFERROR('Cash Flow Data'!G18,0) -> -359 | I86: =IFERROR('Cash Flow Data'!H18,0) -> -222 | ... L86: =IFERROR('Cash Flow Data'!K18,0) -> -29
B87: =IFERROR('Cash Flow Data'!A19,0) -> Issue of shares on acq | C87: =IFERROR('Cash Flow Data'!B19,0) -> 0 | D87: =IFERROR('Cash Flow Data'!C19,0) -> 0 | E87: =IFERROR('Cash Flow Data'!D19,0) -> 0 | F87: =IFERROR('Cash Flow Data'!E19,0) -> 0 | G87: =IFERROR('Cash Flow Data'!F19,0) -> 0 | H87: =IFERROR('Cash Flow Data'!G19,0) -> 0 | I87: =IFERROR('Cash Flow Data'!H19,0) -> 0 | ... L87: =IFERROR('Cash Flow Data'!K19,0) -> 0
B88: =IFERROR('Cash Flow Data'!A20,0) -> Redemp n Canc of Shares | C88: =IFERROR('Cash Flow Data'!B20,0) -> 0 | D88: =IFERROR('Cash Flow Data'!C20,0) -> 88 | E88: =IFERROR('Cash Flow Data'!D20,0) -> 1677 | F88: =IFERROR('Cash Flow Data'!E20,0) -> 717 | G88: =IFERROR('Cash Flow Data'!F20,0) -> 175 | H88: =IFERROR('Cash Flow Data'!G20,0) -> 316 | I88: =IFERROR('Cash Flow Data'!H20,0) -> 617 | ... L88: =IFERROR('Cash Flow Data'!K20,0) -> 0
B89: =IFERROR('Cash Flow Data'!A21,0) -> Acquisition of companies | C89: =IFERROR('Cash Flow Data'!B21,0) -> -208 | D89: =IFERROR('Cash Flow Data'!C21,0) -> -83 | E89: =IFERROR('Cash Flow Data'!D21,0) -> -401 | F89: =IFERROR('Cash Flow Data'!E21,0) -> 0 | G89: =IFERROR('Cash Flow Data'!F21,0) -> -59 | H89: =IFERROR('Cash Flow Data'!G21,0) -> 0 | I89: =IFERROR('Cash Flow Data'!H21,0) -> -42 | ... L89: =IFERROR('Cash Flow Data'!K21,0) -> 0
B90: =IFERROR('Cash Flow Data'!A22,0) -> Inter corporate deposits | C90: =IFERROR('Cash Flow Data'!B22,0) -> 0 | D90: =IFERROR('Cash Flow Data'!C22,0) -> 0 | E90: =IFERROR('Cash Flow Data'!D22,0) -> 0 | F90: =IFERROR('Cash Flow Data'!E22,0) -> 0 | G90: =IFERROR('Cash Flow Data'!F22,0) -> 6 | H90: =IFERROR('Cash Flow Data'!G22,0) -> -262 | I90: =IFERROR('Cash Flow Data'!H22,0) -> -552 | ... L90: =IFERROR('Cash Flow Data'!K22,0) -> 0
B91: =IFERROR('Cash Flow Data'!A23,0) -> Other investing items | C91: =IFERROR('Cash Flow Data'!B23,0) -> -94 | D91: =IFERROR('Cash Flow Data'!C23,0) -> 209 | E91: =IFERROR('Cash Flow Data'!D23,0) -> -290 | F91: =IFERROR('Cash Flow Data'!E23,0) -> -577 | G91: =IFERROR('Cash Flow Data'!F23,0) -> -437 | H91: =IFERROR('Cash Flow Data'!G23,0) -> -7457 | I91: =IFERROR('Cash Flow Data'!H23,0) -> 1494 | ... L91: =IFERROR('Cash Flow Data'!K23,0) -> -6085
B92: Cash from Investing Activity | C92: =IFERROR(SUM(C80:C91),0) -> -5505 | D92: =IFERROR(SUM(D80:D91),0) -> -5874 | E92: =IFERROR(SUM(E80:E91),0) -> -5467 | F92: =IFERROR(SUM(F80:F91),0) -> -7173 | G92: =IFERROR(SUM(G80:G91),0) -> -6869 | H92: =IFERROR(SUM(H80:H91),0) -> -19685 | I92: =IFERROR(SUM(I80:I91),0) -> -3252 | J92: =IFERROR(SUM(J80:J91),0) -> -8867 | ... L92: =IFERROR(SUM(L80:L91),0) -> -18626
B94: Financing Activities
B95: =IFERROR('Cash Flow Data'!A25,0) -> Proceeds from shares | C95: =IFERROR('Cash Flow Data'!B25,0) -> 18 | D95: =IFERROR('Cash Flow Data'!C25,0) -> 12 | E95: =IFERROR('Cash Flow Data'!D25,0) -> 4 | F95: =IFERROR('Cash Flow Data'!E25,0) -> 1 | G95: =IFERROR('Cash Flow Data'!F25,0) -> 1243 | H95: =IFERROR('Cash Flow Data'!G25,0) -> 1 | I95: =IFERROR('Cash Flow Data'!H25,0) -> 1 | ... L95: =IFERROR('Cash Flow Data'!K25,0) -> 1
B96: =IFERROR('Cash Flow Data'!A26,0) -> Proceeds from borrowings | C96: =IFERROR('Cash Flow Data'!B26,0) -> 0 | D96: =IFERROR('Cash Flow Data'!C26,0) -> 0 | E96: =IFERROR('Cash Flow Data'!D26,0) -> 0 | F96: =IFERROR('Cash Flow Data'!E26,0) -> 71389 | G96: =IFERROR('Cash Flow Data'!F26,0) -> 52618 | H96: =IFERROR('Cash Flow Data'!G26,0) -> 38100 | I96: =IFERROR('Cash Flow Data'!H26,0) -> 53880 | ... L96: =IFERROR('Cash Flow Data'!K26,0) -> 84640
B97: =IFERROR('Cash Flow Data'!A27,0) -> Repayment of borrowings | C97: =IFERROR('Cash Flow Data'!B27,0) -> 0 | D97: =IFERROR('Cash Flow Data'!C27,0) -> 0 | E97: =IFERROR('Cash Flow Data'!D27,0) -> 0 | F97: =IFERROR('Cash Flow Data'!E27,0) -> -56352 | G97: =IFERROR('Cash Flow Data'!F27,0) -> -44044 | H97: =IFERROR('Cash Flow Data'!G27,0) -> -37505 | I97: =IFERROR('Cash Flow Data'!H27,0) -> -57223 | ... L97: =IFERROR('Cash Flow Data'!K27,0) -> -64227
B98: =IFERROR('Cash Flow Data'!A28,0) -> Interest paid fin | C98: =IFERROR('Cash Flow Data'!B28,0) -> -443 | D98: =IFERROR('Cash Flow Data'!C28,0) -> -471 | E98: =IFERROR('Cash Flow Data'!D28,0) -> -521 | F98: =IFERROR('Cash Flow Data'!E28,0) -> -723 | G98: =IFERROR('Cash Flow Data'!F28,0) -> -624 | H98: =IFERROR('Cash Flow Data'!G28,0) -> -809 | I98: =IFERROR('Cash Flow Data'!H28,0) -> -680 | ... L98: =IFERROR('Cash Flow Data'!K28,0) -> -436
B99: =IFERROR('Cash Flow Data'!A29,0) -> Dividends paid | C99: =IFERROR('Cash Flow Data'!B29,0) -> -932 | D99: =IFERROR('Cash Flow Data'!C29,0) -> -936 | E99: =IFERROR('Cash Flow Data'!D29,0) -> -963 | F99: =IFERROR('Cash Flow Data'!E29,0) -> -1134 | G99: =IFERROR('Cash Flow Data'!F29,0) -> -1398 | H99: =IFERROR('Cash Flow Data'!G29,0) -> -271 | I99: =IFERROR('Cash Flow Data'!H29,0) -> -1037 | ... L99: =IFERROR('Cash Flow Data'!K29,0) -> -2806
B100: =IFERROR('Cash Flow Data'!A30,0) -> Financial liabilities | C100: =IFERROR('Cash Flow Data'!B30,0) -> 0 | D100: =IFERROR('Cash Flow Data'!C30,0) -> 0 | E100: =IFERROR('Cash Flow Data'!D30,0) -> 0 | F100: =IFERROR('Cash Flow Data'!E30,0) -> 0 | G100: =IFERROR('Cash Flow Data'!F30,0) -> -558 | H100: =IFERROR('Cash Flow Data'!G30,0) -> -553 | I100: =IFERROR('Cash Flow Data'!H30,0) -> -583 | ... L100: =IFERROR('Cash Flow Data'!K30,0) -> -1774
B101: =IFERROR('Cash Flow Data'!A31,0) -> Other financing items | C101: =IFERROR('Cash Flow Data'!B31,0) -> 4324 | D101: =IFERROR('Cash Flow Data'!C31,0) -> 7503 | E101: =IFERROR('Cash Flow Data'!D31,0) -> 7794 | F101: =IFERROR('Cash Flow Data'!E31,0) -> 12 | G101: =IFERROR('Cash Flow Data'!F31,0) -> -304 | H101: =IFERROR('Cash Flow Data'!G31,0) -> 1444 | I101: =IFERROR('Cash Flow Data'!H31,0) -> -240 | ... L101: =IFERROR('Cash Flow Data'!K31,0) -> 437
B102: Cash from Financing Activity | C102: =IFERROR(SUM(C95:C101),0) -> 2967 | D102: =IFERROR(SUM(D95:D101),0) -> 6108 | E102: =IFERROR(SUM(E95:E101),0) -> 6314 | F102: =IFERROR(SUM(F95:F101),0) -> 13193 | G102: =IFERROR(SUM(G95:G101),0) -> 6933 | H102: =IFERROR(SUM(H95:H101),0) -> 407 | I102: =IFERROR(SUM(I95:I101),0) -> -5882 | J102: =IFERROR(SUM(J95:J101),0) -> 15946 | ... L102: =IFERROR(SUM(L95:L101),0) -> 15835
B104: =IFERROR('Cash Flow Data'!A32,0) -> Net Cash Flow | C104: =IFERROR('Cash Flow Data'!B32,0) -> -154 | D104: =IFERROR('Cash Flow Data'!C32,0) -> 416 | E104: =IFERROR('Cash Flow Data'!D32,0) -> 1529 | F104: =IFERROR('Cash Flow Data'!E32,0) -> 1672 | G104: =IFERROR('Cash Flow Data'!F32,0) -> -1394 | H104: =IFERROR('Cash Flow Data'!G32,0) -> -1370 | I104: =IFERROR('Cash Flow Data'!H32,0) -> 113 | ... L104: =IFERROR('Cash Flow Data'!K32,0) -> 384

Sheet DU Pont 
B3: ='[1]Data Sheet'!B1 -> AVENUE SUPERMARTS LTD
B4: (AVANTIFEED | BSE Code: 540376)
B5: ='Data Sheet'!B8 -> 4372.3
B6: 52 Week (High - INR 5484 & Low - 3337.1)
B8: About the company
B9: Avenue Supermarts Limited, d/b/a DMart, is an Indian retail corporation that operates a chain of supermarkets and hypermarkets. The company was founded by Radhakishan Damani and is based in Mumbai. As of March 2025, DMart has 415 stores across 12 states and union territories in India.In March 2024, the company had a total of 13,971 permanent employees and 59,961 employees hired on contractual basis.
B14: Financial Summary
B67: Return on Equity (ROE)
C68: ='Data Sheet'!E16 -> 43555 | D68: ='Data Sheet'!F16 -> 43921 | E68: ='Data Sheet'!G16 -> 44286 | F68: ='Data Sheet'!H16 -> 44651 | G68: ='Data Sheet'!I16 -> 45016 | H68: ='Data Sheet'!J16 -> 45382 | I68: ='Data Sheet'!K16 -> 45747
B69: Net Profit | C69: ='Data Sheet'!E30 -> 902.54 | D69: ='Data Sheet'!F30 -> 1301.08 | E69: ='Data Sheet'!G30 -> 1099.49 | F69: ='Data Sheet'!H30 -> 1492.55 | G69: ='Data Sheet'!I30 -> 2378.51 | H69: ='Data Sheet'!J30 -> 2536.17 | I69: ='Data Sheet'!K30 -> 2708.02
B70: Average Shareholder Equity | C70: =('Data Sheet'!D57+'Data Sheet'!D58)+('Data Sheet'!E57+'Data Sheet'!E58)/2 -> 7462.775 | D70: =('Data Sheet'!E57+'Data Sheet'!E58)+('Data Sheet'!F57+'Data Sheet'!F58)/2 -> 11127.32 | E70: =('Data Sheet'!F57+'Data Sheet'!F58)+('Data Sheet'!G57+'Data Sheet'!G58)/2 -> 17171.595 | F70: =('Data Sheet'!G57+'Data Sheet'!G58)+('Data Sheet'!H57+'Data Sheet'!H58)/2 -> 19022.53 | G70: =('Data Sheet'!H57+'Data Sheet'!H58)+('Data Sheet'!I57+'Data Sheet'!I58)/2 -> 21716.99 | H70: =('Data Sheet'!I57+'Data Sheet'!I58)+('Data Sheet'!J57+'Data Sheet'!J58)/2 -> 25427.61 | I70: =('Data Sheet'!J57+'Data Sheet'!J58)+('Data Sheet'!K57+'Data Sheet'!K58)/2 -> 29411.695
B71: Return on Equity | C71: =C69/C70 -> 0.12093893 | D71: =D69/D70 -> 0.11692663 | E71: =E69/E70 -> 0.064029579 | F71: =F69/F70 -> 0.078462223 | G71: =G69/G70 -> 0.109523 | H71: =H69/H70 -> 0.099740794 | I71: =I69/I70 -> 0.092072898
B73: ROE - Dupont Equation
C74: =C68 -> 43555 | D74: =D68 -> 43921 | E74: =E68 -> 44286 | F74: =F68 -> 44651 | G74: =G68 -> 45016 | H74: =H68 -> 45382 | I74: =I68 -> 45747
B75: =B69 -> Net Profit | C75: =C69 -> 902.54 | D75: =D69 -> 1301.08 | E75: =E69 -> 1099.49 | F75: =F69 -> 1492.55 | G75: =G69 -> 2378.51 | H75: =H69 -> 2536.17 | I75: =I69 -> 2708.02
B76: Revenue | C76: ='Data Sheet'!E17 -> 20004.52 | D76: ='Data Sheet'!F17 -> 24870.2 | E76: ='Data Sheet'!G17 -> 24143.06 | F76: ='Data Sheet'!H17 -> 30976.27 | G76: ='Data Sheet'!I17 -> 42839.56 | H76: ='Data Sheet'!J17 -> 50788.83 | I76: ='Data Sheet'!K17 -> 59358.05
B77: Net Profit Margin (A) | C77: =C75/C76 -> 0.045116804 | D77: =D75/D76 -> 0.052314819 | E77: =E75/E76 -> 0.045540623 | F77: =F75/F76 -> 0.048183658 | G77: =G75/G76 -> 0.055521345 | H77: =H75/H76 -> 0.049935586 | I77: =I75/I76 -> 0.045621782
B79: Revenue | C79: =C76 -> 20004.52 | D79: =D76 -> 24870.2 | E79: =E76 -> 24143.06 | F79: =F76 -> 30976.27 | G79: =G76 -> 42839.56 | H79: =H76 -> 50788.83 | I79: =I76 -> 59358.05
B80: Average Total Asset | C80: =('Data Sheet'!D66+'Data Sheet'!E66)/2 -> 6326.86 | D80: =('Data Sheet'!E66+'Data Sheet'!F66)/2 -> 9540.83 | E80: =('Data Sheet'!F66+'Data Sheet'!G66)/2 -> 12865.605 | F80: =('Data Sheet'!G66+'Data Sheet'!H66)/2 -> 14563.015 | G80: =('Data Sheet'!H66+'Data Sheet'!I66)/2 -> 16787.75 | H80: =('Data Sheet'!I66+'Data Sheet'!J66)/2 -> 19638.5 | I80: =('Data Sheet'!J66+'Data Sheet'!K66)/2 -> 22746.385
B81: Asset Turnover Ratio (B) | C81: =C79/C80 -> 3.1618402 | D81: =D79/D80 -> 2.6067124 | E81: =E79/E80 -> 1.8765585 | F81: =F79/F80 -> 2.1270506 | G81: =G79/G80 -> 2.5518345 | H81: =H79/H80 -> 2.5861868 | I81: =I79/I80 -> 2.6095597
B83: =B80 -> Average Total Asset | C83: =C80 -> 6326.86 | D83: =D80 -> 9540.83 | E83: =E80 -> 12865.605 | F83: =F80 -> 14563.015 | G83: =G80 -> 16787.75 | H83: =H80 -> 19638.5 | I83: =I80 -> 22746.385
B84: =B70 -> Average Shareholder Equity | C84: =C70 -> 7462.775 | D84: =D70 -> 11127.32 | E84: =E70 -> 17171.595 | F84: =F70 -> 19022.53 | G84: =G70 -> 21716.99 | H84: =H70 -> 25427.61 | I84: =I70 -> 29411.695
B85: Equity Multiplier (C) | C85: =C83/C84 -> 0.84778919 | D85: =D83/D84 -> 0.85742389 | E85: =E83/E84 -> 0.74923762 | F85: =F83/F84 -> 0.76556667 | G85: =G83/G84 -> 0.77302379 | H85: =H83/H84 -> 0.77232976 | I85: =I83/I84 -> 0.77337892
B87: Return on Equity (A*B*C) | C87: =C85*C81*C77 -> 0.12093893 | D87: =D85*D81*D77 -> 0.11692663 | E87: =E85*E81*E77 -> 0.064029579 | F87: =F85*F81*F77 -> 0.078462223 | G87: =G85*G81*G77 -> 0.109523 | H87: =H85*H81*H77 -> 0.099740794 | I87: =I85*I81*I77 -> 0.092072898
B89: Return on Asset
C90: =C74 -> 43555 | D90: =D74 -> 43921 | E90: =E74 -> 44286 | F90: =F74 -> 44651 | G90: =G74 -> 45016 | H90: =H74 -> 45382 | I90: =I74 -> 45747
B91: Net Profit | C91: =C75 -> 902.54 | D91: =D75 -> 1301.08 | E91: =E75 -> 1099.49 | F91: =F75 -> 1492.55 | G91: =G75 -> 2378.51 | H91: =H75 -> 2536.17 | I91: =I75 -> 2708.02
B92: =B83 -> Average Total Asset | C92: =C80 -> 6326.86 | D92: =D80 -> 9540.83 | E92: =E80 -> 12865.605 | F92: =F80 -> 14563.015 | G92: =G80 -> 16787.75 | H92: =H80 -> 19638.5 | I92: =I80 -> 22746.385
B93: Return on Asset | C93: =C91/C92 -> 0.14265212 | D93: =D91/D92 -> 0.13636969 | E93: =E91/E92 -> 0.085459642 | F93: =F91/F92 -> 0.10248908 | G93: =G91/G92 -> 0.14168129 | H93: =H91/H92 -> 0.12914276 | I93: =I91/I92 -> 0.11905276
B95: ROA - Dupont Equation
C96: =C90 -> 43555 | D96: =D90 -> 43921 | E96: =E90 -> 44286 | F96: =F90 -> 44651 | G96: =G90 -> 45016 | H96: =H90 -> 45382 | I96: =I90 -> 45747
B97: =B91 -> Net Profit | C97: =C91 -> 902.54 | D97: =D91 -> 1301.08 | E97: =E91 -> 1099.49 | F97: =F91 -> 1492.55 | G97: =G91 -> 2378.51 | H97: =H91 -> 2536.17 | I97: =I91 -> 2708.02
B98: Revenue | C98: =C79 -> 20004.52 | D98: =D79 -> 24870.2 | E98: =E79 -> 24143.06 | F98: =F79 -> 30976.27 | G98: =G79 -> 42839.56 | H98: =H79 -> 50788.83 | I98: =I79 -> 59358.05
B99: Net Profit Margin (A) | C99: =C97/C98 -> 0.045116804 | D99: =D97/D98 -> 0.052314819 | E99: =E97/E98 -> 0.045540623 | F99: =F97/F98 -> 0.048183658 | G99: =G97/G98 -> 0.055521345 | H99: =H97/H98 -> 0.049935586 | I99: =I97/I98 -> 0.045621782
B101: Revenue | C101: =C98 -> 20004.52 | D101: =D98 -> 24870.2 | E101: =E98 -> 24143.06 | F101: =F98 -> 30976.27 | G101: =G98 -> 42839.56 | H101: =H98 -> 50788.83 | I101: =I98 -> 59358.05
B102: Average Total Asset | C102: =C92 -> 6326.86 | D102: =D92 -> 9540.83 | E102: =E92 -> 12865.605 | F102: =F92 -> 14563.015 | G102: =G92 -> 16787.75 | H102: =H92 -> 19638.5 | I102: =I92 -> 22746.385
B103: Asset Turnover Ratio (B) | C103: =C101/C102 -> 3.1618402 | D103: =D101/D102 -> 2.6067124 | E103: =E101/E102 -> 1.8765585 | F103: =F101/F102 -> 2.1270506 | G103: =G101/G102 -> 2.5518345 | H103: =H101/H102 -> 2.5861868 | I103: =I101/I102 -> 2.6095597
B105: Return on Asset (A*B) | C105: =C103*C99 -> 0.14265212 | D105: =D103*D99 -> 0.13636969 | E105: =E103*E99 -> 0.085459642 | F105: =F103*F99 -> 0.10248908 | G105: =G103*G99 -> 0.14168129 | H105: =H103*H99 -> 0.12914276 | I105: =I103*I99 -> 0.11905276
