Workbook

Sheet Implied value
B3: Amount in crores
B4: Comparable Company Valuation
D6: Market Data | K6: Financials | O6: Valuation
B7: Company | D7: Share Price | E7: Shares Outstanding | F7: Equity Value | G7: Net Debt | H7: Enterprise Value | K7: Revenue | L7: EBITDA | M7: Net Income | O7: EV/Revenue | P7: EV/EBITDA | Q7: P/E
B9: ='Data sheet'!C3 -> Sun Pharma.Inds. | D9: ='Data sheet'!D3 -> 1661.15 | E9: ='Data sheet'!E3 -> 239.93 | F9: =D9*E9 -> 398559.72 | G9: ='Data sheet'!G3-'Data sheet'!H3 -> -8969.43 | H9: =F9+G9 -> 389590.29 | K9: ='Data sheet'!I3 -> 52578.44 | L9: ='Data sheet'!L3+'Data sheet'!M3 -> 17236.73 | M9: ='Data sheet'!K3 -> 10964.75 | O9: =$H9/K9 -> 7.4096966 | P9: =$H9/L9 -> 22.602332 | Q9: =F9/M9 -> 36.349184
B10: ='Data sheet'!C4 -> Divi's Lab. | D10: ='Data sheet'!D4 -> 6632.65 | E10: ='Data sheet'!E4 -> 26.55 | F10: =D10*E10 -> 176096.86 | G10: ='Data sheet'!G4-'Data sheet'!H4 -> -3711 | H10: =F10+G10 -> 172385.86 | K10: ='Data sheet'!I4 -> 9360 | L10: ='Data sheet'!L4+'Data sheet'!M4 -> 3320 | M10: ='Data sheet'!K4 -> 2191 | O10: =$H10/K10 -> 18.417292 | P10: =$H10/L10 -> 51.923451 | Q10: =F10/M10 -> 80.372824
B11: ='Data sheet'!C5 -> Cipla | D11: ='Data sheet'!D5 -> 1495.9 | E11: ='Data sheet'!E5 -> 80.77 | F11: =D11*E11 -> 120823.84 | G11: ='Data sheet'!G5-'Data sheet'!H5 -> -361.65 | H11: =F11+G11 -> 120462.19 | K11: ='Data sheet'!I5 -> 27547.62 | L11: ='Data sheet'!L5+'Data sheet'!M5 -> 7989.77 | M11: ='Data sheet'!K5 -> 5269.2 | O11: =$H11/K11 -> 4.3728712 | P11: =$H11/L11 -> 15.077054 | Q11: =F11/M11 -> 22.930206
B12: ='Data sheet'!C6 -> Dr Reddy's Labs | D12: ='Data sheet'!D6 -> 1320.8 | E12: ='Data sheet'!E6 -> 83.46 | F12: =D12*E12 -> 110233.97 | G12: ='Data sheet'!G6-'Data sheet'!H6 -> 2216.4 | H12: =F12+G12 -> 112450.37 | K12: ='Data sheet'!I6 -> 32643.9 | L12: ='Data sheet'!L6+'Data sheet'!M6 -> 9666.1 | M12: ='Data sheet'!K6 -> 5725.2 | O12: =$H12/K12 -> 3.444759 | P12: =$H12/L12 -> 11.633479 | Q12: =F12/M12 -> 19.254169
B13: ='Data sheet'!C7 -> Torrent Pharma. | D13: ='Data sheet'!D7 -> 3165.95 | E13: ='Data sheet'!E7 -> 33.84 | F13: =D13*E13 -> 107135.75 | G13: ='Data sheet'!G7-'Data sheet'!H7 -> 2623 | H13: =F13+G13 -> 109758.75 | K13: ='Data sheet'!I7 -> 11516 | L13: ='Data sheet'!L7+'Data sheet'!M7 -> 3744 | M13: ='Data sheet'!K7 -> 1911 | O13: =$H13/K13 -> 9.5309785 | P13: =$H13/L13 -> 29.315905 | Q13: =F13/M13 -> 56.062662
B14: ='Data sheet'!C8 -> Zydus Lifesci. | D14: ='Data sheet'!D8 -> 956.15 | E14: ='Data sheet'!E8 -> 100.62 | F14: =D14*E14 -> 96207.813 | G14: ='Data sheet'!G8-'Data sheet'!H8 -> 256.4 | H14: =F14+G14 -> 96464.213 | K14: ='Data sheet'!I8 -> 23241.5 | L14: ='Data sheet'!L8+'Data sheet'!M8 -> 7328 | M14: ='Data sheet'!K8 -> 4672.6 | O14: =$H14/K14 -> 4.1505158 | P14: =$H14/L14 -> 13.163785 | Q14: =F14/M14 -> 20.589781
B15: ='Data sheet'!C9 -> Mankind Pharma | D15: ='Data sheet'!D9 -> 2295.1 | E15: ='Data sheet'!E9 -> 41.27 | F15: =D15*E15 -> 94718.777 | G15: ='Data sheet'!G9-'Data sheet'!H9 -> 7956.95 | H15: =F15+G15 -> 102675.73 | K15: ='Data sheet'!I9 -> 12207.44 | L15: ='Data sheet'!L9+'Data sheet'!M9 -> 3566.96 | M15: ='Data sheet'!K9 -> 2011.12 | O15: =$H15/K15 -> 8.4109139 | P15: =$H15/L15 -> 28.78522 | Q15: =F15/M15 -> 47.097526
B16: ='Data sheet'!C10 -> Lupin | D16: ='Data sheet'!D10 -> 1933.9 | E16: ='Data sheet'!E10 -> 45.67 | F16: =D16*E16 -> 88321.213 | G16: ='Data sheet'!G10-'Data sheet'!H10 -> 2305.44 | H16: =F16+G16 -> 90626.653 | K16: ='Data sheet'!I10 -> 22707.9 | L16: ='Data sheet'!L10+'Data sheet'!M10 -> 5479.13 | M16: ='Data sheet'!K10 -> 3306.26 | O16: =$H16/K16 -> 3.9909746 | P16: =$H16/L16 -> 16.540336 | Q16: =F16/M16 -> 26.71333
B17: ='Data sheet'!C11 -> Abbott India | D17: ='Data sheet'!D11 -> 30949 | E17: ='Data sheet'!E11 -> 2.12 | F17: =D17*E17 -> 65611.88 | G17: ='Data sheet'!G11-'Data sheet'!H11 -> -1431.25 | H17: =F17+G17 -> 64180.63 | K17: ='Data sheet'!I11 -> 6409.15 | L17: ='Data sheet'!L11+'Data sheet'!M11 -> 1970.18 | M17: ='Data sheet'!K11 -> 1414.44 | O17: =$H17/K17 -> 10.013907 | P17: =$H17/L17 -> 32.576024 | Q17: =F17/M17 -> 46.387178
B18: ='Data sheet'!C12 -> Aurobindo Pharma | D18: ='Data sheet'!D12 -> 1101.9 | E18: ='Data sheet'!E12 -> 58.59 | F18: =D18*E18 -> 64560.321 | G18: ='Data sheet'!G12-'Data sheet'!H12 -> 27.38 | H18: =F18+G18 -> 64587.701 | K18: ='Data sheet'!I12 -> 31723.73 | L18: ='Data sheet'!L12+'Data sheet'!M12 -> 7172.95 | M18: ='Data sheet'!K12 -> 3483.57 | O18: =$H18/K18 -> 2.0359428 | P18: =$H18/L18 -> 9.0043428 | Q18: =F18/M18 -> 18.532804
B20: High | O20: =MAX(O9:O18) -> 18.417292 | P20: =MAX(P9:P18) -> 51.923451 | Q20: =MAX(Q9:Q18) -> 80.372824
B21: 75th Percentile | O21: =QUARTILE(O9:O18,3) -> 9.2509623 | P21: =QUARTILE(P9:P18,3) -> 29.183234 | Q21: =QUARTILE(Q9:Q18,3) -> 46.919939
B22: Average | O22: =AVERAGE(O9:O18) -> 7.1777852 | P22: =AVERAGE(P9:P18) -> 23.062193 | Q22: =AVERAGE(Q9:Q18) -> 37.428967
B23: Median | O23: =MEDIAN(O9:O18) -> 5.8912839 | P23: =MEDIAN(P9:P18) -> 19.571334 | Q23: =MEDIAN(Q9:Q18) -> 31.531257
B24: 25th Percentile | O24: =QUARTILE(O9:O18,1) -> 4.0308599 | P24: =QUARTILE(P9:P18,1) -> 13.642102 | Q24: =QUARTILE(Q9:Q18,1) -> 21.174888
B25: Low | O25: =MIN(O9:O18) -> 2.0359428 | P25: =MIN(P9:P18) -> 9.0043428 | Q25: =MIN(Q9:Q18) -> 18.532804
B27: Dr Reddy's Labs Comparable valuation | O27: EV/Revenue | P27: EV/EBITDA | Q27: P/E
B29: Implied Enterprise Value | O29: =O23*K12 -> 192314.48 | P29: =P23*L12 -> 189178.47 | Q29: =Q31+Q30 -> 182739.15
B30: Net Debt | O30: =$G$12 -> 2216.4 | P30: =$G$12 -> 2216.4 | Q30: =$G$12 -> 2216.4
B31: Implied Market Value | O31: =O29-O30 -> 190098.08 | P31: =P29-P30 -> 186962.07 | Q31: =Q23*M12 -> 180522.75
B32: Shares Outstanding | O32: =$E$12 -> 83.46 | P32: =$E$12 -> 83.46 | Q32: =$E$12 -> 83.46
B34: Implied Value per Share | O34: =O31/O32 -> 2277.7149 | P34: =P31/P32 -> 2240.1399 | Q34: =Q31/Q32 -> 2162.9853

Sheet Data sheet
B2: S.No. | C2: Name | D2: CMP Rs. | E2: No. Eq. Shares Cr. | F2: Mar Cap Rs.Cr. | G2: Debt Rs.Cr. | H2: Cash End Rs.Cr. | I2: Sales Rs.Cr. | J2: EV Rs.Cr. | K2: NP 12M Rs.Cr. | L2: EBIT 12M Rs.Cr. | M2: Dep 12M Rs.Cr. | N2: EV / EBITDA
B3: 1 | C3: Sun Pharma.Inds. | D3: 1661.15 | E3: 239.93 | F3: 398565.57 | G3: 2362.19 | H3: 11331.62 | I3: 52578.44 | J3: 389596.14 | K3: 10964.75 | L3: 14661.34 | M3: 2575.39 | N3: 22.6
B4: 2 | C4: Divi's Lab. | D4: 6632.65 | E4: 26.55 | F4: 176076.04 | G4: 4 | H4: 3715 | I4: 9360 | J4: 172365.04 | K4: 2191 | L4: 2918 | M4: 402 | N4: 51.92
B5: 3 | C5: Cipla | D5: 1495.9 | E5: 80.77 | F5: 120824.97 | G5: 438.19 | H5: 799.84 | I5: 27547.62 | J5: 120463.32 | K5: 5269.2 | L5: 6882.82 | M5: 1106.95 | N5: 15.08
B6: 4 | C6: Dr Reddy's Labs | D6: 1320.8 | E6: 83.46 | F6: 110222.51 | G6: 4676.6 | H6: 2460.2 | I6: 32643.9 | J6: 112438.91 | K6: 5725.2 | L6: 7962.4 | M6: 1703.7 | N6: 11.63
B7: 5 | C7: Torrent Pharma. | D7: 3165.95 | E7: 33.84 | F7: 107145.31 | G7: 3202 | H7: 579 | I7: 11516 | J7: 109768.31 | K7: 1911 | L7: 2949 | M7: 795 | N7: 29.32
B8: 6 | C8: Zydus Lifesci. | D8: 956.15 | E8: 100.62 | F8: 96211.05 | G8: 3213.2 | H8: 2956.8 | I8: 23241.5 | J8: 96467.45 | K8: 4672.6 | L8: 6412.2 | M8: 915.8 | N8: 13.16
B9: 7 | C9: Mankind Pharma | D9: 2295.1 | E9: 41.27 | F9: 94725.36 | G9: 8511.45 | H9: 554.5 | I9: 12207.44 | J9: 102682.31 | K9: 2011.12 | L9: 2945.74 | M9: 621.22 | N9: 28.79
B10: 8 | C10: Lupin | D10: 1933.9 | E10: 45.67 | F10: 88320.34 | G10: 5447.77 | H10: 3142.33 | I10: 22707.9 | J10: 90625.78 | K10: 3306.26 | L10: 4309.87 | M10: 1169.26 | N10: 16.54
B11: 9 | C11: Abbott India | D11: 30949 | E11: 2.12 | F11: 65766.64 | G11: 196.67 | H11: 1627.92 | I11: 6409.15 | J11: 64335.39 | K11: 1414.44 | L11: 1898.38 | M11: 71.8 | N11: 32.65
B12: 10 | C12: Aurobindo Pharma | D12: 1101.9 | E12: 58.59 | F12: 64564.58 | G12: 8262.87 | H12: 8235.49 | I12: 31723.73 | J12: 64591.96 | K12: 3483.57 | L12: 5523.53 | M12: 1649.42 | N12: 9
